<?xml version="1.0" standalone="yes"?>

<DynamicNetwork><MetaNetwork id="CybHER--A-Method-for-Empowering--Motivating--Educating-and-Anchoring-Girls-to-a-Cybersecurity-Career-Path"><propertyIdentities><propertyIdentity id="Average Words per Sentence" type="number" singleValued="false"/><propertyIdentity id="direction" type="text" singleValued="false"/><propertyIdentity id="Document" type="URI" singleValued="false"/><propertyIdentity id="Number of Characters" type="text" singleValued="false"/><propertyIdentity id="Number of Clauses" type="number" singleValued="false"/><propertyIdentity id="Number of Sentences" type="number" singleValued="false"/><propertyIdentity id="Number of Words" type="number" singleValued="false"/><propertyIdentity id="reset period" type="text" singleValued="false"/><propertyIdentity id="reset type" type="text" singleValued="false"/><propertyIdentity id="step1" type="text" singleValued="false"/><propertyIdentity id="step2" type="text" singleValued="false"/><propertyIdentity id="step3" type="text" singleValued="false"/><propertyIdentity id="step4" type="text" singleValued="false"/><propertyIdentity id="window size" type="text" singleValued="false"/></propertyIdentities><sources><source id="CybHER--A-Method-for-Empowering--Motivating--Educating-and-Anchoring-Girls-to-a-Cybersecurity-Career-Path"><property id="reset period" value="1"/><property id="Number of Characters" value="9634"/><property id="step1" value="PreProcessing/Generalization,useThesauriContentOnly=y,useMasterFormat=n,adjacency=D,outputDirectory=C:/temp/am3temp5577666211300pass1,thesauriLocation=C:UsersgenteDocumentsOntologyResearchBody-AnalysisthesauriAutoMap-CybontoCore-Full-New.csv,inputDirectory=C:/temp/am3temp5577666211300sentSplit"/><property id="Number of Words" value="254"/><property id="Number of Clauses" value="940"/><property id="window size" value="2147483"/><property id="step3" value="Processing/SemanticNetwork,windowSize=2,directional=B,useAllWordsAsWindowSize=y,resetNumber=1,textUnit=S,inputDirectory=C:/temp/am3temp5577666211300pass1"/><property id="Document" value="C:/temp/am3temp5577666211300pass1CybHER--A-Method-for-Empowering--Motivating--Educating-and-Anchoring-Girls-to-a-Cybersecurity-Career-Path.txt"/><property id="Average Words per Sentence" value="0.55"/><property id="step2" value="Processing/SemanticNetwork,windowSize=2,directional=B,useAllWordsAsWindowSize=y,outputDirectory=C:UsersgenteDocumentsOntologyResearchBody-AnalysisAutoMap-SemanticNet-ResultsSemanticNet1,resetNumber=1,textUnit=S,inputDirectory=C:/temp/am3temp5577666211300pass1"/><property id="direction" value="B"/><property id="step4" value="PostProcessing/UnionDynetml,outputDirectory=C:UsersgenteDocumentsOntologyResearchBody-AnalysisAutoMap-SemanticNet-ResultsSemanticNet1union,unionType=s"/><property id="Number of Sentences" value="459"/><property id="reset type" value="S"/></source></sources><nodes><nodeclass type="Unknown" id="Unknown"><propertyIdentities><propertyIdentity id="Action" type="text" singleValued="false"/><propertyIdentity id="Evaluation" type="text" singleValued="false"/><propertyIdentity id="frequency" type="number" singleValued="false"/><propertyIdentity id="gram_type" type="categoryText" singleValued="false"/><propertyIdentity id="number_of_texts" type="text" singleValued="false"/><propertyIdentity id="Potency" type="text" singleValued="false"/><propertyIdentity id="relative_frequency-within_text" type="text" singleValued="false"/></propertyIdentities><node id="-408"><property id="Action" value=" "/><property id="Potency" value=" "/><property id="Evaluation" value=" "/><property id="gram_type" value="single"/><property id="frequency" value="1"/><property id="number_of_texts" value="1"/><property id="relative_frequency-within_text" value="0.04761905"/></node><node id="appraisal"><property id="Action" value=" "/><property id="Potency" value=" "/><property id="Evaluation" value=" "/><property id="gram_type" value="single"/><property id="frequency" value="2"/><property id="number_of_texts" value="1"/><property id="relative_frequency-within_text" value="0.0952381"/></node><node id="attending"><property id="Action" value=" "/><property id="Potency" value=" "/><property id="Evaluation" value=" "/><property id="gram_type" value="single"/><property id="frequency" value="1"/><property id="number_of_texts" value="1"/><property id="relative_frequency-within_text" value="0.04761905"/></node><node id="behavior_control-ability"><property id="Action" value=" "/><property id="Potency" value=" "/><property id="Evaluation" value=" "/><property id="gram_type" value="ngram"/><property id="frequency" value="3"/><property id="number_of_texts" value="1"/><property id="relative_frequency-within_text" value="0.14285715"/></node><node id="certainty_effect"><property id="Action" value=" "/><property id="Potency" value=" "/><property id="Evaluation" value=" "/><property id="gram_type" value="ngram"/><property id="frequency" value="11"/><property id="number_of_texts" value="1"/><property id="relative_frequency-within_text" value="0.52380955"/></node><node id="combining"><property id="Action" value=" "/><property id="Potency" value=" "/><property id="Evaluation" value=" "/><property id="gram_type" value="single"/><property id="frequency" value="7"/><property id="number_of_texts" value="1"/><property id="relative_frequency-within_text" value="0.33333334"/></node><node id="efficacy"><property id="Action" value=" "/><property id="Potency" value=" "/><property id="Evaluation" value=" "/><property id="gram_type" value="single"/><property id="frequency" value="1"/><property id="number_of_texts" value="1"/><property id="relative_frequency-within_text" value="0.04761905"/></node><node id="emotional_intelligence"><property id="Action" value=" "/><property id="Potency" value=" "/><property id="Evaluation" value=" "/><property id="gram_type" value="ngram"/><property id="frequency" value="1"/><property id="number_of_texts" value="1"/><property id="relative_frequency-within_text" value="0.04761905"/></node><node id="evaluating"><property id="Action" value=" "/><property id="Potency" value=" "/><property id="Evaluation" value=" "/><property id="gram_type" value="single"/><property id="frequency" value="2"/><property id="number_of_texts" value="1"/><property id="relative_frequency-within_text" value="0.0952381"/></node><node id="experience"><property id="Action" value=" "/><property id="Potency" value=" "/><property id="Evaluation" value=" "/><property id="gram_type" value="single"/><property id="frequency" value="5"/><property id="number_of_texts" value="1"/><property id="relative_frequency-within_text" value="0.23809524"/></node><node id="exposure"><property id="Action" value=" "/><property id="Potency" value=" "/><property id="Evaluation" value=" "/><property id="gram_type" value="single"/><property id="frequency" value="1"/><property id="number_of_texts" value="1"/><property id="relative_frequency-within_text" value="0.04761905"/></node><node id="extrinsic_rewards"><property id="Action" value=" "/><property id="Potency" value=" "/><property id="Evaluation" value=" "/><property id="gram_type" value="ngram"/><property id="frequency" value="8"/><property id="number_of_texts" value="1"/><property id="relative_frequency-within_text" value="0.3809524"/></node><node id="fear_arousal"><property id="Action" value=" "/><property id="Potency" value=" "/><property id="Evaluation" value=" "/><property id="gram_type" value="ngram"/><property id="frequency" value="1"/><property id="number_of_texts" value="1"/><property id="relative_frequency-within_text" value="0.04761905"/></node><node id="focus"><property id="Action" value=" "/><property id="Potency" value=" "/><property id="Evaluation" value=" "/><property id="gram_type" value="single"/><property id="frequency" value="7"/><property id="number_of_texts" value="1"/><property id="relative_frequency-within_text" value="0.33333334"/></node><node id="gain"><property id="Action" value=" "/><property id="Potency" value=" "/><property id="Evaluation" value=" "/><property id="gram_type" value="single"/><property id="frequency" value="5"/><property id="number_of_texts" value="1"/><property id="relative_frequency-within_text" value="0.23809524"/></node><node id="goal"><property id="Action" value=" "/><property id="Potency" value=" "/><property id="Evaluation" value=" "/><property id="gram_type" value="single"/><property id="frequency" value="1"/><property id="number_of_texts" value="1"/><property id="relative_frequency-within_text" value="0.04761905"/></node><node id="imagination"><property id="Action" value=" "/><property id="Potency" value=" "/><property id="Evaluation" value=" "/><property id="gram_type" value="single"/><property id="frequency" value="2"/><property id="number_of_texts" value="1"/><property id="relative_frequency-within_text" value="0.0952381"/></node><node id="impact"><property id="Action" value=" "/><property id="Potency" value=" "/><property id="Evaluation" value=" "/><property id="gram_type" value="single"/><property id="frequency" value="3"/><property id="number_of_texts" value="1"/><property id="relative_frequency-within_text" value="0.14285715"/></node><node id="intelligence"><property id="Action" value=" "/><property id="Potency" value=" "/><property id="Evaluation" value=" "/><property id="gram_type" value="single"/><property id="frequency" value="7"/><property id="number_of_texts" value="1"/><property id="relative_frequency-within_text" value="0.33333334"/></node><node id="intentionality"><property id="Action" value=" "/><property id="Potency" value=" "/><property id="Evaluation" value=" "/><property id="gram_type" value="single"/><property id="frequency" value="1"/><property id="number_of_texts" value="1"/><property id="relative_frequency-within_text" value="0.04761905"/></node><node id="intrinsic_rewards"><property id="Action" value=" "/><property id="Potency" value=" "/><property id="Evaluation" value=" "/><property id="gram_type" value="ngram"/><property id="frequency" value="4"/><property id="number_of_texts" value="1"/><property id="relative_frequency-within_text" value="0.1904762"/></node><node id="isolation_effect"><property id="Action" value=" "/><property id="Potency" value=" "/><property id="Evaluation" value=" "/><property id="gram_type" value="ngram"/><property id="frequency" value="2"/><property id="number_of_texts" value="1"/><property id="relative_frequency-within_text" value="0.0952381"/></node><node id="judging"><property id="Action" value=" "/><property id="Potency" value=" "/><property id="Evaluation" value=" "/><property id="gram_type" value="single"/><property id="frequency" value="1"/><property id="number_of_texts" value="1"/><property id="relative_frequency-within_text" value="0.04761905"/></node><node id="knowledge"><property id="Action" value=" "/><property id="Potency" value=" "/><property id="Evaluation" value=" "/><property id="gram_type" value="single"/><property id="frequency" value="7"/><property id="number_of_texts" value="1"/><property id="relative_frequency-within_text" value="0.33333334"/></node><node id="learning"><property id="Action" value=" "/><property id="Potency" value=" "/><property id="Evaluation" value=" "/><property id="gram_type" value="single"/><property id="frequency" value="13"/><property id="number_of_texts" value="1"/><property id="relative_frequency-within_text" value="0.61904764"/></node><node id="long"><property id="Action" value=" "/><property id="Potency" value=" "/><property id="Evaluation" value=" "/><property id="gram_type" value="single"/><property id="frequency" value="1"/><property id="number_of_texts" value="1"/><property id="relative_frequency-within_text" value="0.04761905"/></node><node id="loss"><property id="Action" value=" "/><property id="Potency" value=" "/><property id="Evaluation" value=" "/><property id="gram_type" value="single"/><property id="frequency" value="8"/><property id="number_of_texts" value="1"/><property id="relative_frequency-within_text" value="0.3809524"/></node><node id="mastery_experience"><property id="Action" value=" "/><property id="Potency" value=" "/><property id="Evaluation" value=" "/><property id="gram_type" value="ngram"/><property id="frequency" value="2"/><property id="number_of_texts" value="1"/><property id="relative_frequency-within_text" value="0.0952381"/></node><node id="mental_calculation"><property id="Action" value=" "/><property id="Potency" value=" "/><property id="Evaluation" value=" "/><property id="gram_type" value="ngram"/><property id="frequency" value="1"/><property id="number_of_texts" value="1"/><property id="relative_frequency-within_text" value="0.04761905"/></node><node id="motivation"><property id="Action" value=" "/><property id="Potency" value=" "/><property id="Evaluation" value=" "/><property id="gram_type" value="single"/><property id="frequency" value="5"/><property id="number_of_texts" value="1"/><property id="relative_frequency-within_text" value="0.23809524"/></node><node id="participant_modeling"><property id="Action" value=" "/><property id="Potency" value=" "/><property id="Evaluation" value=" "/><property id="gram_type" value="ngram"/><property id="frequency" value="5"/><property id="number_of_texts" value="1"/><property id="relative_frequency-within_text" value="0.23809524"/></node><node id="perceived_consensus"><property id="Action" value=" "/><property id="Potency" value=" "/><property id="Evaluation" value=" "/><property id="gram_type" value="ngram"/><property id="frequency" value="1"/><property id="number_of_texts" value="1"/><property id="relative_frequency-within_text" value="0.04761905"/></node><node id="perceived_responsibility"><property id="Action" value=" "/><property id="Potency" value=" "/><property id="Evaluation" value=" "/><property id="gram_type" value="ngram"/><property id="frequency" value="6"/><property id="number_of_texts" value="1"/><property id="relative_frequency-within_text" value="0.2857143"/></node><node id="perceived_uniqueness"><property id="Action" value=" "/><property id="Potency" value=" "/><property id="Evaluation" value=" "/><property id="gram_type" value="ngram"/><property id="frequency" value="7"/><property id="number_of_texts" value="1"/><property id="relative_frequency-within_text" value="0.33333334"/></node><node id="perceived_vulnerability"><property id="Action" value=" "/><property id="Potency" value=" "/><property id="Evaluation" value=" "/><property id="gram_type" value="ngram"/><property id="frequency" value="2"/><property id="number_of_texts" value="1"/><property id="relative_frequency-within_text" value="0.0952381"/></node><node id="perception"><property id="Action" value=" "/><property id="Potency" value=" "/><property id="Evaluation" value=" "/><property id="gram_type" value="single"/><property id="frequency" value="11"/><property id="number_of_texts" value="1"/><property id="relative_frequency-within_text" value="0.52380955"/></node><node id="persistence"><property id="Action" value=" "/><property id="Potency" value=" "/><property id="Evaluation" value=" "/><property id="gram_type" value="single"/><property id="frequency" value="5"/><property id="number_of_texts" value="1"/><property id="relative_frequency-within_text" value="0.23809524"/></node><node id="personality"><property id="Action" value=" "/><property id="Potency" value=" "/><property id="Evaluation" value=" "/><property id="gram_type" value="single"/><property id="frequency" value="21"/><property id="number_of_texts" value="1"/><property id="relative_frequency-within_text" value="1.0"/></node><node id="phishing"><property id="Action" value=" "/><property id="Potency" value=" "/><property id="Evaluation" value=" "/><property id="gram_type" value="single"/><property id="frequency" value="1"/><property id="number_of_texts" value="1"/><property id="relative_frequency-within_text" value="0.04761905"/></node><node id="physical_quality"><property id="Action" value=" "/><property id="Potency" value=" "/><property id="Evaluation" value=" "/><property id="gram_type" value="ngram"/><property id="frequency" value="4"/><property id="number_of_texts" value="1"/><property id="relative_frequency-within_text" value="0.1904762"/></node><node id="possibility_effect"><property id="Action" value=" "/><property id="Potency" value=" "/><property id="Evaluation" value=" "/><property id="gram_type" value="ngram"/><property id="frequency" value="2"/><property id="number_of_texts" value="1"/><property id="relative_frequency-within_text" value="0.0952381"/></node><node id="protection_effect"><property id="Action" value=" "/><property id="Potency" value=" "/><property id="Evaluation" value=" "/><property id="gram_type" value="ngram"/><property id="frequency" value="10"/><property id="number_of_texts" value="1"/><property id="relative_frequency-within_text" value="0.47619048"/></node><node id="reliance"><property id="Action" value=" "/><property id="Potency" value=" "/><property id="Evaluation" value=" "/><property id="gram_type" value="single"/><property id="frequency" value="1"/><property id="number_of_texts" value="1"/><property id="relative_frequency-within_text" value="0.04761905"/></node><node id="satisfaction_of_needs"><property id="Action" value=" "/><property id="Potency" value=" "/><property id="Evaluation" value=" "/><property id="gram_type" value="ngram"/><property id="frequency" value="6"/><property id="number_of_texts" value="1"/><property id="relative_frequency-within_text" value="0.2857143"/></node><node id="self-efficacy"><property id="Action" value=" "/><property id="Potency" value=" "/><property id="Evaluation" value=" "/><property id="gram_type" value="single"/><property id="frequency" value="4"/><property id="number_of_texts" value="1"/><property id="relative_frequency-within_text" value="0.1904762"/></node><node id="skill"><property id="Action" value=" "/><property id="Potency" value=" "/><property id="Evaluation" value=" "/><property id="gram_type" value="single"/><property id="frequency" value="1"/><property id="number_of_texts" value="1"/><property id="relative_frequency-within_text" value="0.04761905"/></node><node id="syllogistic_rules"><property id="Action" value=" "/><property id="Potency" value=" "/><property id="Evaluation" value=" "/><property id="gram_type" value="ngram"/><property id="frequency" value="7"/><property id="number_of_texts" value="1"/><property id="relative_frequency-within_text" value="0.33333334"/></node><node id="techniques"><property id="Action" value=" "/><property id="Potency" value=" "/><property id="Evaluation" value=" "/><property id="gram_type" value="single"/><property id="frequency" value="11"/><property id="number_of_texts" value="1"/><property id="relative_frequency-within_text" value="0.52380955"/></node><node id="thinking"><property id="Action" value=" "/><property id="Potency" value=" "/><property id="Evaluation" value=" "/><property id="gram_type" value="single"/><property id="frequency" value="1"/><property id="number_of_texts" value="1"/><property id="relative_frequency-within_text" value="0.04761905"/></node><node id="to-student"><property id="Action" value=" "/><property id="Potency" value=" "/><property id="Evaluation" value=" "/><property id="gram_type" value="single"/><property id="frequency" value="1"/><property id="number_of_texts" value="1"/><property id="relative_frequency-within_text" value="0.04761905"/></node><node id="&#8226;"><property id="Action" value=" "/><property id="Potency" value=" "/><property id="Evaluation" value=" "/><property id="gram_type" value="single"/><property id="frequency" value="4"/><property id="number_of_texts" value="1"/><property id="relative_frequency-within_text" value="0.1904762"/></node></nodeclass><nodeclass type="Belief" id="Belief"><propertyIdentities><propertyIdentity id="Action" type="text" singleValued="false"/><propertyIdentity id="Evaluation" type="text" singleValued="false"/><propertyIdentity id="frequency" type="number" singleValued="false"/><propertyIdentity id="gram_type" type="categoryText" singleValued="false"/><propertyIdentity id="number_of_texts" type="text" singleValued="false"/><propertyIdentity id="Potency" type="text" singleValued="false"/><propertyIdentity id="relative_frequency-within_text" type="text" singleValued="false"/></propertyIdentities><node id="belief"><property id="gram_type" value="single"/><property id="Evaluation" value=" "/><property id="number_of_texts" value="1"/><property id="relative_frequency-within_text" value="0.7619048"/><property id="Potency" value=" "/><property id="Action" value=" "/><property id="frequency" value="16"/></node></nodeclass><nodeclass type="Organization" id="Organization"><propertyIdentities><propertyIdentity id="Action" type="text" singleValued="false"/><propertyIdentity id="Evaluation" type="text" singleValued="false"/><propertyIdentity id="frequency" type="number" singleValued="false"/><propertyIdentity id="gram_type" type="categoryText" singleValued="false"/><propertyIdentity id="number_of_texts" type="text" singleValued="false"/><propertyIdentity id="Potency" type="text" singleValued="false"/><propertyIdentity id="relative_frequency-within_text" type="text" singleValued="false"/></propertyIdentities><node id="organization"><property id="frequency" value="4"/><property id="gram_type" value="single"/><property id="number_of_texts" value="1"/><property id="Evaluation" value=" "/><property id="Potency" value=" "/><property id="Action" value=" "/><property id="relative_frequency-within_text" value="0.1904762"/></node></nodeclass><nodeclass type="Resource" id="Resource"><propertyIdentities><propertyIdentity id="Action" type="text" singleValued="false"/><propertyIdentity id="Evaluation" type="text" singleValued="false"/><propertyIdentity id="frequency" type="number" singleValued="false"/><propertyIdentity id="gram_type" type="categoryText" singleValued="false"/><propertyIdentity id="number_of_texts" type="text" singleValued="false"/><propertyIdentity id="Potency" type="text" singleValued="false"/><propertyIdentity id="relative_frequency-within_text" type="text" singleValued="false"/></propertyIdentities><node id="resource"><property id="Potency" value=" "/><property id="Evaluation" value=" "/><property id="Action" value=" "/><property id="number_of_texts" value="1"/><property id="frequency" value="2"/><property id="relative_frequency-within_text" value="0.0952381"/><property id="gram_type" value="single"/></node></nodeclass><nodeclass type="Role" id="Role"><propertyIdentities><propertyIdentity id="Action" type="text" singleValued="false"/><propertyIdentity id="Evaluation" type="text" singleValued="false"/><propertyIdentity id="frequency" type="number" singleValued="false"/><propertyIdentity id="gram_type" type="categoryText" singleValued="false"/><propertyIdentity id="number_of_texts" type="text" singleValued="false"/><propertyIdentity id="Potency" type="text" singleValued="false"/><propertyIdentity id="relative_frequency-within_text" type="text" singleValued="false"/></propertyIdentities><node id="role"><property id="relative_frequency-within_text" value="0.1904762"/><property id="gram_type" value="single"/><property id="Potency" value=" "/><property id="frequency" value="4"/><property id="Action" value=" "/><property id="number_of_texts" value="1"/><property id="Evaluation" value=" "/></node></nodeclass><nodeclass type="Task" id="Task"><propertyIdentities><propertyIdentity id="Action" type="text" singleValued="false"/><propertyIdentity id="Evaluation" type="text" singleValued="false"/><propertyIdentity id="frequency" type="number" singleValued="false"/><propertyIdentity id="gram_type" type="categoryText" singleValued="false"/><propertyIdentity id="number_of_texts" type="text" singleValued="false"/><propertyIdentity id="Potency" type="text" singleValued="false"/><propertyIdentity id="relative_frequency-within_text" type="text" singleValued="false"/></propertyIdentities><node id="task"><property id="Action" value=" "/><property id="number_of_texts" value="1"/><property id="frequency" value="1"/><property id="Evaluation" value=" "/><property id="gram_type" value="single"/><property id="Potency" value=" "/><property id="relative_frequency-within_text" value="0.04761905"/></node></nodeclass></nodes><networks><network sourceType="Unknown" source="Unknown" targetType="Unknown" target="Unknown" id="Unknown x Unknown" isDirected="false" allowSelfLoops="false" isBinary="false"><propertyIdentities><propertyIdentity id="average distance" type="number" singleValued="false"/><propertyIdentity id="shortest distance" type="number" singleValued="false"/></propertyIdentities><link source="protection_effect" target="phishing" value="2.0"><property id="average distance" value="1.0"/><property id="shortest distance" value="1.0"/></link><link source="protection_effect" target="physical_quality" value="2.0"><property id="average distance" value="2.0"/><property id="shortest distance" value="2.0"/></link><link source="protection_effect" target="certainty_effect" value="6.0"><property id="average distance" value="1.3333334"/><property id="shortest distance" value="1.3333334"/></link><link source="protection_effect" target="intelligence" value="2.0"><property id="average distance" value="3.0"/><property id="shortest distance" value="3.0"/></link><link source="protection_effect" target="satisfaction_of_needs" value="2.0"><property id="average distance" value="2.0"/><property id="shortest distance" value="2.0"/></link><link source="protection_effect" target="appraisal" value="2.0"><property id="average distance" value="1.0"/><property id="shortest distance" value="1.0"/></link><link source="protection_effect" target="combining" value="2.0"><property id="average distance" value="1.0"/><property id="shortest distance" value="1.0"/></link><link source="protection_effect" target="extrinsic_rewards" value="2.0"><property id="average distance" value="2.0"/><property id="shortest distance" value="2.0"/></link><link source="protection_effect" target="loss" value="2.0"><property id="average distance" value="1.0"/><property id="shortest distance" value="1.0"/></link><link source="protection_effect" target="perception" value="2.0"><property id="average distance" value="1.0"/><property id="shortest distance" value="1.0"/></link><link source="protection_effect" target="personality" value="2.0"><property id="average distance" value="2.0"/><property id="shortest distance" value="2.0"/></link><link source="satisfaction_of_needs" target="physical_quality" value="2.0"><property id="average distance" value="2.0"/><property id="shortest distance" value="2.0"/></link><link source="satisfaction_of_needs" target="certainty_effect" value="4.0"><property id="average distance" value="1.0"/><property id="shortest distance" value="1.0"/></link><link source="satisfaction_of_needs" target="protection_effect" value="2.0"><property id="average distance" value="2.0"/><property id="shortest distance" value="2.0"/></link><link source="satisfaction_of_needs" target="experience" value="2.0"><property id="average distance" value="1.0"/><property id="shortest distance" value="1.0"/></link><link source="satisfaction_of_needs" target="motivation" value="2.0"><property id="average distance" value="4.0"/><property id="shortest distance" value="4.0"/></link><link source="satisfaction_of_needs" target="combining" value="2.0"><property id="average distance" value="1.0"/><property id="shortest distance" value="1.0"/></link><link source="exposure" target="certainty_effect" value="2.0"><property id="average distance" value="1.0"/><property id="shortest distance" value="1.0"/></link><link source="exposure" target="perceived_responsibility" value="2.0"><property id="average distance" value="1.0"/><property id="shortest distance" value="1.0"/></link><link source="intrinsic_rewards" target="perceived_responsibility" value="2.0"><property id="average distance" value="2.0"/><property id="shortest distance" value="2.0"/></link><link source="intrinsic_rewards" target="experience" value="4.0"><property id="average distance" value="1.0"/><property id="shortest distance" value="1.0"/></link><link source="intrinsic_rewards" target="learning" value="4.0"><property id="average distance" value="2.0"/><property id="shortest distance" value="2.0"/></link><link source="intrinsic_rewards" target="gain" value="2.0"><property id="average distance" value="1.0"/><property id="shortest distance" value="1.0"/></link><link source="imagination" target="perceived_uniqueness" value="2.0"><property id="average distance" value="2.0"/><property id="shortest distance" value="2.0"/></link><link source="imagination" target="motivation" value="2.0"><property id="average distance" value="2.0"/><property id="shortest distance" value="2.0"/></link><link source="imagination" target="techniques" value="4.0"><property id="average distance" value="1.0"/><property id="shortest distance" value="1.0"/></link><link source="behavior_control-ability" target="evaluating" value="4.0"><property id="average distance" value="1.5"/><property id="shortest distance" value="1.5"/></link><link source="behavior_control-ability" target="focus" value="2.0"><property id="average distance" value="1.0"/><property id="shortest distance" value="1.0"/></link><link source="mental_calculation" target="gain" value="2.0"><property id="average distance" value="1.0"/><property id="shortest distance" value="1.0"/></link><link source="phishing" target="physical_quality" value="2.0"><property id="average distance" value="1.0"/><property id="shortest distance" value="1.0"/></link><link source="phishing" target="protection_effect" value="2.0"><property id="average distance" value="1.0"/><property id="shortest distance" value="1.0"/></link><link source="phishing" target="intelligence" value="2.0"><property id="average distance" value="2.0"/><property id="shortest distance" value="2.0"/></link><link source="focus" target="physical_quality" value="2.0"><property id="average distance" value="2.0"/><property id="shortest distance" value="2.0"/></link><link source="focus" target="syllogistic_rules" value="2.0"><property id="average distance" value="1.0"/><property id="shortest distance" value="1.0"/></link><link source="focus" target="perceived_uniqueness" value="2.0"><property id="average distance" value="2.0"/><property id="shortest distance" value="2.0"/></link><link source="focus" target="perceived_responsibility" value="2.0"><property id="average distance" value="1.0"/><property id="shortest distance" value="1.0"/></link><link source="focus" target="participant_modeling" value="2.0"><property id="average distance" value="1.0"/><property id="shortest distance" value="1.0"/></link><link source="focus" target="judging" value="2.0"><property id="average distance" value="2.0"/><property id="shortest distance" value="2.0"/></link><link source="focus" target="behavior_control-ability" value="2.0"><property id="average distance" value="1.0"/><property id="shortest distance" value="1.0"/></link><link source="focus" target="intentionality" value="2.0"><property id="average distance" value="1.0"/><property id="shortest distance" value="1.0"/></link><link source="certainty_effect" target="physical_quality" value="2.0"><property id="average distance" value="1.0"/><property id="shortest distance" value="1.0"/></link><link source="certainty_effect" target="protection_effect" value="6.0"><property id="average distance" value="1.3333334"/><property id="shortest distance" value="1.3333334"/></link><link source="certainty_effect" target="perceived_uniqueness" value="2.0"><property id="average distance" value="1.0"/><property id="shortest distance" value="1.0"/></link><link source="certainty_effect" target="satisfaction_of_needs" value="4.0"><property id="average distance" value="1.0"/><property id="shortest distance" value="1.0"/></link><link source="certainty_effect" target="exposure" value="2.0"><property id="average distance" value="1.0"/><property id="shortest distance" value="1.0"/></link><link source="certainty_effect" target="perceived_responsibility" value="2.0"><property id="average distance" value="2.0"/><property id="shortest distance" value="2.0"/></link><link source="certainty_effect" target="motivation" value="2.0"><property id="average distance" value="3.0"/><property id="shortest distance" value="3.0"/></link><link source="certainty_effect" target="learning" value="4.0"><property id="average distance" value="1.5"/><property id="shortest distance" value="1.5"/></link><link source="certainty_effect" target="extrinsic_rewards" value="2.0"><property id="average distance" value="3.0"/><property id="shortest distance" value="3.0"/></link><link source="certainty_effect" target="loss" value="2.0"><property id="average distance" value="2.0"/><property id="shortest distance" value="2.0"/></link><link source="certainty_effect" target="personality" value="10.0"><property id="average distance" value="1.2"/><property id="shortest distance" value="1.2"/></link><link source="perceived_uniqueness" target="certainty_effect" value="2.0"><property id="average distance" value="1.0"/><property id="shortest distance" value="1.0"/></link><link source="perceived_uniqueness" target="focus" value="2.0"><property id="average distance" value="2.0"/><property id="shortest distance" value="2.0"/></link><link source="perceived_uniqueness" target="syllogistic_rules" value="2.0"><property id="average distance" value="1.0"/><property id="shortest distance" value="1.0"/></link><link source="perceived_uniqueness" target="imagination" value="2.0"><property id="average distance" value="2.0"/><property id="shortest distance" value="2.0"/></link><link source="perceived_uniqueness" target="motivation" value="2.0"><property id="average distance" value="4.0"/><property id="shortest distance" value="4.0"/></link><link source="perceived_uniqueness" target="intentionality" value="2.0"><property id="average distance" value="3.0"/><property id="shortest distance" value="3.0"/></link><link source="perceived_uniqueness" target="personality" value="4.0"><property id="average distance" value="2.5"/><property id="shortest distance" value="2.5"/></link><link source="perceived_uniqueness" target="techniques" value="4.0"><property id="average distance" value="2.0"/><property id="shortest distance" value="2.0"/></link><link source="experience" target="satisfaction_of_needs" value="2.0"><property id="average distance" value="1.0"/><property id="shortest distance" value="1.0"/></link><link source="experience" target="intrinsic_rewards" value="4.0"><property id="average distance" value="1.0"/><property id="shortest distance" value="1.0"/></link><link source="experience" target="perceived_responsibility" value="2.0"><property id="average distance" value="1.0"/><property id="shortest distance" value="1.0"/></link><link source="experience" target="learning" value="6.0"><property id="average distance" value="1.6666666"/><property id="shortest distance" value="1.6666666"/></link><link source="possibility_effect" target="impact" value="2.0"><property id="average distance" value="1.0"/><property id="shortest distance" value="1.0"/></link><link source="judging" target="focus" value="2.0"><property id="average distance" value="2.0"/><property id="shortest distance" value="2.0"/></link><link source="attending" target="learning" value="2.0"><property id="average distance" value="2.0"/><property id="shortest distance" value="2.0"/></link><link source="attending" target="gain" value="2.0"><property id="average distance" value="1.0"/><property id="shortest distance" value="1.0"/></link><link source="motivation" target="physical_quality" value="2.0"><property id="average distance" value="2.0"/><property id="shortest distance" value="2.0"/></link><link source="motivation" target="certainty_effect" value="2.0"><property id="average distance" value="3.0"/><property id="shortest distance" value="3.0"/></link><link source="motivation" target="perceived_uniqueness" value="2.0"><property id="average distance" value="4.0"/><property id="shortest distance" value="4.0"/></link><link source="motivation" target="satisfaction_of_needs" value="2.0"><property id="average distance" value="4.0"/><property id="shortest distance" value="4.0"/></link><link source="motivation" target="imagination" value="2.0"><property id="average distance" value="2.0"/><property id="shortest distance" value="2.0"/></link><link source="motivation" target="impact" value="2.0"><property id="average distance" value="1.0"/><property id="shortest distance" value="1.0"/></link><link source="motivation" target="personality" value="2.0"><property id="average distance" value="2.0"/><property id="shortest distance" value="2.0"/></link><link source="motivation" target="techniques" value="4.0"><property id="average distance" value="2.0"/><property id="shortest distance" value="2.0"/></link><link source="combining" target="protection_effect" value="2.0"><property id="average distance" value="1.0"/><property id="shortest distance" value="1.0"/></link><link source="combining" target="satisfaction_of_needs" value="2.0"><property id="average distance" value="1.0"/><property id="shortest distance" value="1.0"/></link><link source="combining" target="perception" value="2.0"><property id="average distance" value="1.0"/><property id="shortest distance" value="1.0"/></link><link source="combining" target="personality" value="4.0"><property id="average distance" value="1.5"/><property id="shortest distance" value="1.5"/></link><link source="learning" target="certainty_effect" value="4.0"><property id="average distance" value="1.5"/><property id="shortest distance" value="1.5"/></link><link source="learning" target="intrinsic_rewards" value="4.0"><property id="average distance" value="2.0"/><property id="shortest distance" value="2.0"/></link><link source="learning" target="perceived_responsibility" value="2.0"><property id="average distance" value="1.0"/><property id="shortest distance" value="1.0"/></link><link source="learning" target="experience" value="6.0"><property id="average distance" value="1.6666666"/><property id="shortest distance" value="1.6666666"/></link><link source="learning" target="attending" value="2.0"><property id="average distance" value="2.0"/><property id="shortest distance" value="2.0"/></link><link source="learning" target="gain" value="2.0"><property id="average distance" value="1.0"/><property id="shortest distance" value="1.0"/></link><link source="learning" target="personality" value="2.0"><property id="average distance" value="1.0"/><property id="shortest distance" value="1.0"/></link><link source="intentionality" target="focus" value="2.0"><property id="average distance" value="1.0"/><property id="shortest distance" value="1.0"/></link><link source="intentionality" target="syllogistic_rules" value="2.0"><property id="average distance" value="2.0"/><property id="shortest distance" value="2.0"/></link><link source="intentionality" target="perceived_uniqueness" value="2.0"><property id="average distance" value="3.0"/><property id="shortest distance" value="3.0"/></link><link source="perceived_vulnerability" target="perceived_responsibility" value="4.0"><property id="average distance" value="1.5"/><property id="shortest distance" value="1.5"/></link><link source="perception" target="protection_effect" value="2.0"><property id="average distance" value="1.0"/><property id="shortest distance" value="1.0"/></link><link source="perception" target="appraisal" value="2.0"><property id="average distance" value="1.0"/><property id="shortest distance" value="1.0"/></link><link source="perception" target="combining" value="2.0"><property id="average distance" value="1.0"/><property id="shortest distance" value="1.0"/></link><link source="perception" target="gain" value="2.0"><property id="average distance" value="1.0"/><property id="shortest distance" value="1.0"/></link><link source="impact" target="possibility_effect" value="2.0"><property id="average distance" value="1.0"/><property id="shortest distance" value="1.0"/></link><link source="impact" target="motivation" value="2.0"><property id="average distance" value="1.0"/><property id="shortest distance" value="1.0"/></link><link source="impact" target="extrinsic_rewards" value="2.0"><property id="average distance" value="2.0"/><property id="shortest distance" value="2.0"/></link><link source="impact" target="techniques" value="2.0"><property id="average distance" value="1.0"/><property id="shortest distance" value="1.0"/></link><link source="physical_quality" target="phishing" value="2.0"><property id="average distance" value="1.0"/><property id="shortest distance" value="1.0"/></link><link source="physical_quality" target="certainty_effect" value="2.0"><property id="average distance" value="1.0"/><property id="shortest distance" value="1.0"/></link><link source="physical_quality" target="focus" value="2.0"><property id="average distance" value="2.0"/><property id="shortest distance" value="2.0"/></link><link source="physical_quality" target="protection_effect" value="2.0"><property id="average distance" value="2.0"/><property id="shortest distance" value="2.0"/></link><link source="physical_quality" target="intelligence" value="2.0"><property id="average distance" value="1.0"/><property id="shortest distance" value="1.0"/></link><link source="physical_quality" target="satisfaction_of_needs" value="2.0"><property id="average distance" value="2.0"/><property id="shortest distance" value="2.0"/></link><link source="physical_quality" target="perceived_responsibility" value="2.0"><property id="average distance" value="1.0"/><property id="shortest distance" value="1.0"/></link><link source="physical_quality" target="motivation" value="2.0"><property id="average distance" value="2.0"/><property id="shortest distance" value="2.0"/></link><link source="intelligence" target="phishing" value="2.0"><property id="average distance" value="2.0"/><property id="shortest distance" value="2.0"/></link><link source="intelligence" target="physical_quality" value="2.0"><property id="average distance" value="1.0"/><property id="shortest distance" value="1.0"/></link><link source="intelligence" target="protection_effect" value="2.0"><property id="average distance" value="3.0"/><property id="shortest distance" value="3.0"/></link><link source="intelligence" target="participant_modeling" value="2.0"><property id="average distance" value="1.0"/><property id="shortest distance" value="1.0"/></link><link source="intelligence" target="techniques" value="2.0"><property id="average distance" value="2.0"/><property id="shortest distance" value="2.0"/></link><link source="participant_modeling" target="focus" value="2.0"><property id="average distance" value="1.0"/><property id="shortest distance" value="1.0"/></link><link source="participant_modeling" target="intelligence" value="2.0"><property id="average distance" value="1.0"/><property id="shortest distance" value="1.0"/></link><link source="participant_modeling" target="extrinsic_rewards" value="4.0"><property id="average distance" value="2.0"/><property id="shortest distance" value="2.0"/></link><link source="participant_modeling" target="techniques" value="2.0"><property id="average distance" value="1.0"/><property id="shortest distance" value="1.0"/></link><link source="self-efficacy" target="knowledge" value="2.0"><property id="average distance" value="2.0"/><property id="shortest distance" value="2.0"/></link><link source="self-efficacy" target="personality" value="4.0"><property id="average distance" value="1.0"/><property id="shortest distance" value="1.0"/></link><link source="appraisal" target="protection_effect" value="2.0"><property id="average distance" value="1.0"/><property id="shortest distance" value="1.0"/></link><link source="appraisal" target="perception" value="2.0"><property id="average distance" value="1.0"/><property id="shortest distance" value="1.0"/></link><link source="gain" target="intrinsic_rewards" value="2.0"><property id="average distance" value="1.0"/><property id="shortest distance" value="1.0"/></link><link source="gain" target="attending" value="2.0"><property id="average distance" value="1.0"/><property id="shortest distance" value="1.0"/></link><link source="gain" target="learning" value="2.0"><property id="average distance" value="1.0"/><property id="shortest distance" value="1.0"/></link><link source="gain" target="mental_calculation" value="2.0"><property id="average distance" value="1.0"/><property id="shortest distance" value="1.0"/></link><link source="gain" target="perception" value="2.0"><property id="average distance" value="1.0"/><property id="shortest distance" value="1.0"/></link><link source="personality" target="certainty_effect" value="10.0"><property id="average distance" value="1.2"/><property id="shortest distance" value="1.2"/></link><link source="personality" target="syllogistic_rules" value="2.0"><property id="average distance" value="1.0"/><property id="shortest distance" value="1.0"/></link><link source="personality" target="protection_effect" value="2.0"><property id="average distance" value="2.0"/><property id="shortest distance" value="2.0"/></link><link source="personality" target="perceived_uniqueness" value="4.0"><property id="average distance" value="2.5"/><property id="shortest distance" value="2.5"/></link><link source="personality" target="self-efficacy" value="4.0"><property id="average distance" value="1.0"/><property id="shortest distance" value="1.0"/></link><link source="personality" target="motivation" value="2.0"><property id="average distance" value="2.0"/><property id="shortest distance" value="2.0"/></link><link source="personality" target="combining" value="4.0"><property id="average distance" value="1.5"/><property id="shortest distance" value="1.5"/></link><link source="personality" target="learning" value="2.0"><property id="average distance" value="1.0"/><property id="shortest distance" value="1.0"/></link><link source="personality" target="extrinsic_rewards" value="2.0"><property id="average distance" value="4.0"/><property id="shortest distance" value="4.0"/></link><link source="personality" target="loss" value="6.0"><property id="average distance" value="2.6666667"/><property id="shortest distance" value="2.6666667"/></link><link source="techniques" target="intelligence" value="2.0"><property id="average distance" value="2.0"/><property id="shortest distance" value="2.0"/></link><link source="techniques" target="knowledge" value="4.0"><property id="average distance" value="1.5"/><property id="shortest distance" value="1.5"/></link><link source="techniques" target="perceived_uniqueness" value="4.0"><property id="average distance" value="2.0"/><property id="shortest distance" value="2.0"/></link><link source="techniques" target="imagination" value="4.0"><property id="average distance" value="1.0"/><property id="shortest distance" value="1.0"/></link><link source="techniques" target="participant_modeling" value="2.0"><property id="average distance" value="1.0"/><property id="shortest distance" value="1.0"/></link><link source="techniques" target="motivation" value="4.0"><property id="average distance" value="2.0"/><property id="shortest distance" value="2.0"/></link><link source="techniques" target="skill" value="4.0"><property id="average distance" value="2.5"/><property id="shortest distance" value="2.5"/></link><link source="techniques" target="extrinsic_rewards" value="2.0"><property id="average distance" value="1.0"/><property id="shortest distance" value="1.0"/></link><link source="techniques" target="impact" value="2.0"><property id="average distance" value="1.0"/><property id="shortest distance" value="1.0"/></link><link source="evaluating" target="behavior_control-ability" value="4.0"><property id="average distance" value="1.5"/><property id="shortest distance" value="1.5"/></link><link source="syllogistic_rules" target="focus" value="2.0"><property id="average distance" value="1.0"/><property id="shortest distance" value="1.0"/></link><link source="syllogistic_rules" target="knowledge" value="2.0"><property id="average distance" value="1.0"/><property id="shortest distance" value="1.0"/></link><link source="syllogistic_rules" target="perceived_uniqueness" value="2.0"><property id="average distance" value="1.0"/><property id="shortest distance" value="1.0"/></link><link source="syllogistic_rules" target="intentionality" value="2.0"><property id="average distance" value="2.0"/><property id="shortest distance" value="2.0"/></link><link source="syllogistic_rules" target="loss" value="4.0"><property id="average distance" value="1.5"/><property id="shortest distance" value="1.5"/></link><link source="syllogistic_rules" target="personality" value="2.0"><property id="average distance" value="1.0"/><property id="shortest distance" value="1.0"/></link><link source="knowledge" target="syllogistic_rules" value="2.0"><property id="average distance" value="1.0"/><property id="shortest distance" value="1.0"/></link><link source="knowledge" target="self-efficacy" value="2.0"><property id="average distance" value="2.0"/><property id="shortest distance" value="2.0"/></link><link source="knowledge" target="skill" value="2.0"><property id="average distance" value="1.0"/><property id="shortest distance" value="1.0"/></link><link source="knowledge" target="techniques" value="4.0"><property id="average distance" value="1.5"/><property id="shortest distance" value="1.5"/></link><link source="perceived_responsibility" target="physical_quality" value="2.0"><property id="average distance" value="1.0"/><property id="shortest distance" value="1.0"/></link><link source="perceived_responsibility" target="certainty_effect" value="2.0"><property id="average distance" value="2.0"/><property id="shortest distance" value="2.0"/></link><link source="perceived_responsibility" target="focus" value="2.0"><property id="average distance" value="1.0"/><property id="shortest distance" value="1.0"/></link><link source="perceived_responsibility" target="exposure" value="2.0"><property id="average distance" value="1.0"/><property id="shortest distance" value="1.0"/></link><link source="perceived_responsibility" target="intrinsic_rewards" value="2.0"><property id="average distance" value="2.0"/><property id="shortest distance" value="2.0"/></link><link source="perceived_responsibility" target="experience" value="2.0"><property id="average distance" value="1.0"/><property id="shortest distance" value="1.0"/></link><link source="perceived_responsibility" target="learning" value="2.0"><property id="average distance" value="1.0"/><property id="shortest distance" value="1.0"/></link><link source="perceived_responsibility" target="perceived_vulnerability" value="4.0"><property id="average distance" value="1.5"/><property id="shortest distance" value="1.5"/></link><link source="skill" target="knowledge" value="2.0"><property id="average distance" value="1.0"/><property id="shortest distance" value="1.0"/></link><link source="skill" target="techniques" value="4.0"><property id="average distance" value="2.5"/><property id="shortest distance" value="2.5"/></link><link source="extrinsic_rewards" target="certainty_effect" value="2.0"><property id="average distance" value="3.0"/><property id="shortest distance" value="3.0"/></link><link source="extrinsic_rewards" target="protection_effect" value="2.0"><property id="average distance" value="2.0"/><property id="shortest distance" value="2.0"/></link><link source="extrinsic_rewards" target="participant_modeling" value="4.0"><property id="average distance" value="2.0"/><property id="shortest distance" value="2.0"/></link><link source="extrinsic_rewards" target="impact" value="2.0"><property id="average distance" value="2.0"/><property id="shortest distance" value="2.0"/></link><link source="extrinsic_rewards" target="loss" value="2.0"><property id="average distance" value="1.0"/><property id="shortest distance" value="1.0"/></link><link source="extrinsic_rewards" target="personality" value="2.0"><property id="average distance" value="4.0"/><property id="shortest distance" value="4.0"/></link><link source="extrinsic_rewards" target="techniques" value="2.0"><property id="average distance" value="1.0"/><property id="shortest distance" value="1.0"/></link><link source="loss" target="certainty_effect" value="2.0"><property id="average distance" value="2.0"/><property id="shortest distance" value="2.0"/></link><link source="loss" target="syllogistic_rules" value="4.0"><property id="average distance" value="1.5"/><property id="shortest distance" value="1.5"/></link><link source="loss" target="protection_effect" value="2.0"><property id="average distance" value="1.0"/><property id="shortest distance" value="1.0"/></link><link source="loss" target="extrinsic_rewards" value="2.0"><property id="average distance" value="1.0"/><property id="shortest distance" value="1.0"/></link><link source="loss" target="personality" value="6.0"><property id="average distance" value="2.6666667"/><property id="shortest distance" value="2.6666667"/></link></network><network sourceType="Belief" source="Belief" targetType="Belief" target="Belief" id="Belief x Belief" isDirected="false" allowSelfLoops="false" isBinary="false"></network><network sourceType="Belief" source="Belief" targetType="Unknown" target="Unknown" id="Belief x Unknown" isDirected="true" allowSelfLoops="true" isBinary="false"><propertyIdentities><propertyIdentity id="average distance" type="number" singleValued="false"/><propertyIdentity id="shortest distance" type="number" singleValued="false"/></propertyIdentities><link source="belief" target="physical_quality" value="2.0"><property id="average distance" value="1.0"/><property id="shortest distance" value="1.0"/></link><link source="belief" target="certainty_effect" value="2.0"><property id="average distance" value="2.0"/><property id="shortest distance" value="2.0"/></link><link source="belief" target="focus" value="2.0"><property id="average distance" value="1.0"/><property id="shortest distance" value="1.0"/></link><link source="belief" target="syllogistic_rules" value="4.0"><property id="average distance" value="1.0"/><property id="shortest distance" value="1.0"/></link><link source="belief" target="knowledge" value="4.0"><property id="average distance" value="1.5"/><property id="shortest distance" value="1.5"/></link><link source="belief" target="satisfaction_of_needs" value="2.0"><property id="average distance" value="3.0"/><property id="shortest distance" value="3.0"/></link><link source="belief" target="self-efficacy" value="2.0"><property id="average distance" value="1.0"/><property id="shortest distance" value="1.0"/></link><link source="belief" target="judging" value="2.0"><property id="average distance" value="1.0"/><property id="shortest distance" value="1.0"/></link><link source="belief" target="motivation" value="4.0"><property id="average distance" value="1.0"/><property id="shortest distance" value="1.0"/></link><link source="belief" target="extrinsic_rewards" value="2.0"><property id="average distance" value="1.0"/><property id="shortest distance" value="1.0"/></link><link source="belief" target="loss" value="4.0"><property id="average distance" value="1.5"/><property id="shortest distance" value="1.5"/></link><link source="belief" target="personality" value="8.0"><property id="average distance" value="1.25"/><property id="shortest distance" value="1.25"/></link></network><network sourceType="Role" source="Role" targetType="Unknown" target="Unknown" id="Role x Unknown" isDirected="true" allowSelfLoops="true" isBinary="false"><propertyIdentities><propertyIdentity id="average distance" type="number" singleValued="false"/><propertyIdentity id="shortest distance" type="number" singleValued="false"/></propertyIdentities><link source="role" target="certainty_effect" value="2.0"><property id="average distance" value="1.0"/><property id="shortest distance" value="1.0"/></link><link source="role" target="protection_effect" value="4.0"><property id="average distance" value="1.5"/><property id="shortest distance" value="1.5"/></link><link source="role" target="thinking" value="2.0"><property id="average distance" value="1.0"/><property id="shortest distance" value="1.0"/></link></network><network sourceType="Organization" source="Organization" targetType="Unknown" target="Unknown" id="Organization x Unknown" isDirected="true" allowSelfLoops="true" isBinary="false"><propertyIdentities><propertyIdentity id="average distance" type="number" singleValued="false"/><propertyIdentity id="shortest distance" type="number" singleValued="false"/></propertyIdentities><link source="organization" target="perceived_uniqueness" value="2.0"><property id="average distance" value="1.0"/><property id="shortest distance" value="1.0"/></link><link source="organization" target="satisfaction_of_needs" value="2.0"><property id="average distance" value="2.0"/><property id="shortest distance" value="2.0"/></link><link source="organization" target="intrinsic_rewards" value="2.0"><property id="average distance" value="2.0"/><property id="shortest distance" value="2.0"/></link><link source="organization" target="experience" value="4.0"><property id="average distance" value="2.0"/><property id="shortest distance" value="2.0"/></link><link source="organization" target="learning" value="2.0"><property id="average distance" value="1.0"/><property id="shortest distance" value="1.0"/></link></network><network sourceType="Task" source="Task" targetType="Unknown" target="Unknown" id="Task x Unknown" isDirected="true" allowSelfLoops="true" isBinary="false"><propertyIdentities><propertyIdentity id="average distance" type="number" singleValued="false"/><propertyIdentity id="shortest distance" type="number" singleValued="false"/></propertyIdentities><link source="task" target="intrinsic_rewards" value="2.0"><property id="average distance" value="1.0"/><property id="shortest distance" value="1.0"/></link><link source="task" target="perceived_responsibility" value="2.0"><property id="average distance" value="3.0"/><property id="shortest distance" value="3.0"/></link><link source="task" target="experience" value="2.0"><property id="average distance" value="2.0"/><property id="shortest distance" value="2.0"/></link><link source="task" target="learning" value="2.0"><property id="average distance" value="4.0"/><property id="shortest distance" value="4.0"/></link></network><network sourceType="Resource" source="Resource" targetType="Unknown" target="Unknown" id="Resource x Unknown" isDirected="true" allowSelfLoops="true" isBinary="false"><propertyIdentities><propertyIdentity id="average distance" type="number" singleValued="false"/><propertyIdentity id="shortest distance" type="number" singleValued="false"/></propertyIdentities><link source="resource" target="participant_modeling" value="4.0"><property id="average distance" value="1.0"/><property id="shortest distance" value="1.0"/></link><link source="resource" target="extrinsic_rewards" value="4.0"><property id="average distance" value="1.0"/><property id="shortest distance" value="1.0"/></link></network></networks></MetaNetwork></DynamicNetwork>

