<?xml version="1.0" standalone="yes"?>

<DynamicNetwork><MetaNetwork id="Effect-of-intrusion-detection-and-response-on-reliability-of-cyber-physical-systems"><propertyIdentities><propertyIdentity id="Average Words per Sentence" type="number" singleValued="false"/><propertyIdentity id="direction" type="text" singleValued="false"/><propertyIdentity id="Document" type="URI" singleValued="false"/><propertyIdentity id="Number of Characters" type="text" singleValued="false"/><propertyIdentity id="Number of Clauses" type="number" singleValued="false"/><propertyIdentity id="Number of Sentences" type="number" singleValued="false"/><propertyIdentity id="Number of Words" type="number" singleValued="false"/><propertyIdentity id="reset period" type="text" singleValued="false"/><propertyIdentity id="reset type" type="text" singleValued="false"/><propertyIdentity id="step1" type="text" singleValued="false"/><propertyIdentity id="step2" type="text" singleValued="false"/><propertyIdentity id="step3" type="text" singleValued="false"/><propertyIdentity id="step4" type="text" singleValued="false"/><propertyIdentity id="window size" type="text" singleValued="false"/></propertyIdentities><sources><source id="Effect-of-intrusion-detection-and-response-on-reliability-of-cyber-physical-systems"><property id="step2" value="Processing/SemanticNetwork,windowSize=2,directional=B,useAllWordsAsWindowSize=y,outputDirectory=C:UsersgenteDocumentsOntologyResearchBody-AnalysisAutoMap-SemanticNet-ResultsSemanticNet1,resetNumber=1,textUnit=S,inputDirectory=C:/temp/am3temp5577666211300pass1"/><property id="Document" value="C:/temp/am3temp5577666211300pass1Effect-of-intrusion-detection-and-response-on-reliability-of-cyber-physical-systems.txt"/><property id="Number of Sentences" value="769"/><property id="direction" value="B"/><property id="reset period" value="1"/><property id="step4" value="PostProcessing/UnionDynetml,outputDirectory=C:UsersgenteDocumentsOntologyResearchBody-AnalysisAutoMap-SemanticNet-ResultsSemanticNet1union,unionType=s"/><property id="Average Words per Sentence" value="0.69"/><property id="reset type" value="S"/><property id="Number of Characters" value="18349"/><property id="step1" value="PreProcessing/Generalization,useThesauriContentOnly=y,useMasterFormat=n,adjacency=D,outputDirectory=C:/temp/am3temp5577666211300pass1,thesauriLocation=C:UsersgenteDocumentsOntologyResearchBody-AnalysisthesauriAutoMap-CybontoCore-Full-New.csv,inputDirectory=C:/temp/am3temp5577666211300sentSplit"/><property id="window size" value="2147483"/><property id="step3" value="Processing/SemanticNetwork,windowSize=2,directional=B,useAllWordsAsWindowSize=y,resetNumber=1,textUnit=S,inputDirectory=C:/temp/am3temp5577666211300pass1"/><property id="Number of Clauses" value="1471"/><property id="Number of Words" value="533"/></source></sources><nodes><nodeclass type="Unknown" id="Unknown"><propertyIdentities><propertyIdentity id="Action" type="text" singleValued="false"/><propertyIdentity id="Evaluation" type="text" singleValued="false"/><propertyIdentity id="frequency" type="number" singleValued="false"/><propertyIdentity id="gram_type" type="categoryText" singleValued="false"/><propertyIdentity id="number_of_texts" type="text" singleValued="false"/><propertyIdentity id="Potency" type="text" singleValued="false"/><propertyIdentity id="relative_frequency-within_text" type="text" singleValued="false"/></propertyIdentities><node id="appraisal"><property id="Action" value=" "/><property id="number_of_texts" value="1"/><property id="Potency" value=" "/><property id="Evaluation" value=" "/><property id="frequency" value="9"/><property id="relative_frequency-within_text" value="0.08490566"/><property id="gram_type" value="single"/></node><node id="behavior"><property id="Action" value=" "/><property id="number_of_texts" value="1"/><property id="Potency" value=" "/><property id="Evaluation" value=" "/><property id="frequency" value="14"/><property id="relative_frequency-within_text" value="0.13207547"/><property id="gram_type" value="single"/></node><node id="behavior_control-ability"><property id="Action" value=" "/><property id="number_of_texts" value="1"/><property id="Potency" value=" "/><property id="Evaluation" value=" "/><property id="frequency" value="3"/><property id="relative_frequency-within_text" value="0.028301887"/><property id="gram_type" value="ngram"/></node><node id="certainty_effect"><property id="Action" value=" "/><property id="number_of_texts" value="1"/><property id="Potency" value=" "/><property id="Evaluation" value=" "/><property id="frequency" value="21"/><property id="relative_frequency-within_text" value="0.1981132"/><property id="gram_type" value="ngram"/></node><node id="coding"><property id="Action" value=" "/><property id="number_of_texts" value="1"/><property id="Potency" value=" "/><property id="Evaluation" value=" "/><property id="frequency" value="1"/><property id="relative_frequency-within_text" value="0.009433962"/><property id="gram_type" value="single"/></node><node id="collection"><property id="Action" value=" "/><property id="number_of_texts" value="1"/><property id="Potency" value=" "/><property id="Evaluation" value=" "/><property id="frequency" value="1"/><property id="relative_frequency-within_text" value="0.009433962"/><property id="gram_type" value="single"/></node><node id="combining"><property id="Action" value=" "/><property id="number_of_texts" value="1"/><property id="Potency" value=" "/><property id="Evaluation" value=" "/><property id="frequency" value="15"/><property id="relative_frequency-within_text" value="0.14150943"/><property id="gram_type" value="single"/></node><node id="comply_effect"><property id="Action" value=" "/><property id="number_of_texts" value="1"/><property id="Potency" value=" "/><property id="Evaluation" value=" "/><property id="frequency" value="10"/><property id="relative_frequency-within_text" value="0.094339624"/><property id="gram_type" value="ngram"/></node><node id="division"><property id="Action" value=" "/><property id="number_of_texts" value="1"/><property id="Potency" value=" "/><property id="Evaluation" value=" "/><property id="frequency" value="2"/><property id="relative_frequency-within_text" value="0.018867925"/><property id="gram_type" value="single"/></node><node id="evaluating"><property id="Action" value=" "/><property id="number_of_texts" value="1"/><property id="Potency" value=" "/><property id="Evaluation" value=" "/><property id="frequency" value="17"/><property id="relative_frequency-within_text" value="0.16037735"/><property id="gram_type" value="single"/></node><node id="experiential_awareness"><property id="Action" value=" "/><property id="number_of_texts" value="1"/><property id="Potency" value=" "/><property id="Evaluation" value=" "/><property id="frequency" value="2"/><property id="relative_frequency-within_text" value="0.018867925"/><property id="gram_type" value="ngram"/></node><node id="extrinsic_rewards"><property id="Action" value=" "/><property id="number_of_texts" value="1"/><property id="Potency" value=" "/><property id="Evaluation" value=" "/><property id="frequency" value="3"/><property id="relative_frequency-within_text" value="0.028301887"/><property id="gram_type" value="ngram"/></node><node id="focus"><property id="Action" value=" "/><property id="number_of_texts" value="1"/><property id="Potency" value=" "/><property id="Evaluation" value=" "/><property id="frequency" value="11"/><property id="relative_frequency-within_text" value="0.10377359"/><property id="gram_type" value="single"/></node><node id="function"><property id="Action" value=" "/><property id="number_of_texts" value="1"/><property id="Potency" value=" "/><property id="Evaluation" value=" "/><property id="frequency" value="8"/><property id="relative_frequency-within_text" value="0.0754717"/><property id="gram_type" value="single"/></node><node id="gain"><property id="Action" value=" "/><property id="number_of_texts" value="1"/><property id="Potency" value=" "/><property id="Evaluation" value=" "/><property id="frequency" value="12"/><property id="relative_frequency-within_text" value="0.11320755"/><property id="gram_type" value="single"/></node><node id="generalizing"><property id="Action" value=" "/><property id="number_of_texts" value="1"/><property id="Potency" value=" "/><property id="Evaluation" value=" "/><property id="frequency" value="1"/><property id="relative_frequency-within_text" value="0.009433962"/><property id="gram_type" value="single"/></node><node id="goal"><property id="Action" value=" "/><property id="number_of_texts" value="1"/><property id="Potency" value=" "/><property id="Evaluation" value=" "/><property id="frequency" value="3"/><property id="relative_frequency-within_text" value="0.028301887"/><property id="gram_type" value="single"/></node><node id="history"><property id="Action" value=" "/><property id="number_of_texts" value="1"/><property id="Potency" value=" "/><property id="Evaluation" value=" "/><property id="frequency" value="2"/><property id="relative_frequency-within_text" value="0.018867925"/><property id="gram_type" value="single"/></node><node id="intentionality"><property id="Action" value=" "/><property id="number_of_texts" value="1"/><property id="Potency" value=" "/><property id="Evaluation" value=" "/><property id="frequency" value="2"/><property id="relative_frequency-within_text" value="0.018867925"/><property id="gram_type" value="single"/></node><node id="internalization"><property id="Action" value=" "/><property id="number_of_texts" value="1"/><property id="Potency" value=" "/><property id="Evaluation" value=" "/><property id="frequency" value="1"/><property id="relative_frequency-within_text" value="0.009433962"/><property id="gram_type" value="single"/></node><node id="intrinsic_rewards"><property id="Action" value=" "/><property id="number_of_texts" value="1"/><property id="Potency" value=" "/><property id="Evaluation" value=" "/><property id="frequency" value="17"/><property id="relative_frequency-within_text" value="0.16037735"/><property id="gram_type" value="ngram"/></node><node id="isolation_effect"><property id="Action" value=" "/><property id="number_of_texts" value="1"/><property id="Potency" value=" "/><property id="Evaluation" value=" "/><property id="frequency" value="4"/><property id="relative_frequency-within_text" value="0.03773585"/><property id="gram_type" value="ngram"/></node><node id="judging"><property id="Action" value=" "/><property id="number_of_texts" value="1"/><property id="Potency" value=" "/><property id="Evaluation" value=" "/><property id="frequency" value="7"/><property id="relative_frequency-within_text" value="0.06603774"/><property id="gram_type" value="single"/></node><node id="knowledge"><property id="Action" value=" "/><property id="number_of_texts" value="1"/><property id="Potency" value=" "/><property id="Evaluation" value=" "/><property id="frequency" value="1"/><property id="relative_frequency-within_text" value="0.009433962"/><property id="gram_type" value="single"/></node><node id="learning"><property id="Action" value=" "/><property id="number_of_texts" value="1"/><property id="Potency" value=" "/><property id="Evaluation" value=" "/><property id="frequency" value="3"/><property id="relative_frequency-within_text" value="0.028301887"/><property id="gram_type" value="single"/></node><node id="loss"><property id="Action" value=" "/><property id="number_of_texts" value="1"/><property id="Potency" value=" "/><property id="Evaluation" value=" "/><property id="frequency" value="106"/><property id="relative_frequency-within_text" value="1.0"/><property id="gram_type" value="single"/></node><node id="mental_calculation"><property id="Action" value=" "/><property id="number_of_texts" value="1"/><property id="Potency" value=" "/><property id="Evaluation" value=" "/><property id="frequency" value="13"/><property id="relative_frequency-within_text" value="0.12264151"/><property id="gram_type" value="ngram"/></node><node id="participant_modeling"><property id="Action" value=" "/><property id="number_of_texts" value="1"/><property id="Potency" value=" "/><property id="Evaluation" value=" "/><property id="frequency" value="16"/><property id="relative_frequency-within_text" value="0.1509434"/><property id="gram_type" value="ngram"/></node><node id="perceived_consensus"><property id="Action" value=" "/><property id="number_of_texts" value="1"/><property id="Potency" value=" "/><property id="Evaluation" value=" "/><property id="frequency" value="1"/><property id="relative_frequency-within_text" value="0.009433962"/><property id="gram_type" value="ngram"/></node><node id="perceived_responsibility"><property id="Action" value=" "/><property id="number_of_texts" value="1"/><property id="Potency" value=" "/><property id="Evaluation" value=" "/><property id="frequency" value="1"/><property id="relative_frequency-within_text" value="0.009433962"/><property id="gram_type" value="ngram"/></node><node id="perceived_vulnerability"><property id="Action" value=" "/><property id="number_of_texts" value="1"/><property id="Potency" value=" "/><property id="Evaluation" value=" "/><property id="frequency" value="67"/><property id="relative_frequency-within_text" value="0.6320755"/><property id="gram_type" value="ngram"/></node><node id="perception"><property id="Action" value=" "/><property id="number_of_texts" value="1"/><property id="Potency" value=" "/><property id="Evaluation" value=" "/><property id="frequency" value="8"/><property id="relative_frequency-within_text" value="0.0754717"/><property id="gram_type" value="single"/></node><node id="persistence"><property id="Action" value=" "/><property id="number_of_texts" value="1"/><property id="Potency" value=" "/><property id="Evaluation" value=" "/><property id="frequency" value="2"/><property id="relative_frequency-within_text" value="0.018867925"/><property id="gram_type" value="single"/></node><node id="personality"><property id="Action" value=" "/><property id="number_of_texts" value="1"/><property id="Potency" value=" "/><property id="Evaluation" value=" "/><property id="frequency" value="92"/><property id="relative_frequency-within_text" value="0.8679245"/><property id="gram_type" value="single"/></node><node id="physical_quality"><property id="Action" value=" "/><property id="number_of_texts" value="1"/><property id="Potency" value=" "/><property id="Evaluation" value=" "/><property id="frequency" value="1"/><property id="relative_frequency-within_text" value="0.009433962"/><property id="gram_type" value="ngram"/></node><node id="planning"><property id="Action" value=" "/><property id="number_of_texts" value="1"/><property id="Potency" value=" "/><property id="Evaluation" value=" "/><property id="frequency" value="2"/><property id="relative_frequency-within_text" value="0.018867925"/><property id="gram_type" value="single"/></node><node id="possibility_effect"><property id="Action" value=" "/><property id="number_of_texts" value="1"/><property id="Potency" value=" "/><property id="Evaluation" value=" "/><property id="frequency" value="8"/><property id="relative_frequency-within_text" value="0.0754717"/><property id="gram_type" value="ngram"/></node><node id="process"><property id="Action" value=" "/><property id="number_of_texts" value="1"/><property id="Potency" value=" "/><property id="Evaluation" value=" "/><property id="frequency" value="5"/><property id="relative_frequency-within_text" value="0.047169812"/><property id="gram_type" value="single"/></node><node id="protection_effect"><property id="Action" value=" "/><property id="number_of_texts" value="1"/><property id="Potency" value=" "/><property id="Evaluation" value=" "/><property id="frequency" value="10"/><property id="relative_frequency-within_text" value="0.094339624"/><property id="gram_type" value="ngram"/></node><node id="satisfaction_of_needs"><property id="Action" value=" "/><property id="number_of_texts" value="1"/><property id="Potency" value=" "/><property id="Evaluation" value=" "/><property id="frequency" value="2"/><property id="relative_frequency-within_text" value="0.018867925"/><property id="gram_type" value="ngram"/></node><node id="segregating"><property id="Action" value=" "/><property id="number_of_texts" value="1"/><property id="Potency" value=" "/><property id="Evaluation" value=" "/><property id="frequency" value="2"/><property id="relative_frequency-within_text" value="0.018867925"/><property id="gram_type" value="single"/></node><node id="simplifying"><property id="Action" value=" "/><property id="number_of_texts" value="1"/><property id="Potency" value=" "/><property id="Evaluation" value=" "/><property id="frequency" value="7"/><property id="relative_frequency-within_text" value="0.06603774"/><property id="gram_type" value="single"/></node><node id="social_circumstance"><property id="Action" value=" "/><property id="number_of_texts" value="1"/><property id="Potency" value=" "/><property id="Evaluation" value=" "/><property id="frequency" value="1"/><property id="relative_frequency-within_text" value="0.009433962"/><property id="gram_type" value="ngram"/></node><node id="syllogistic_rules"><property id="Action" value=" "/><property id="number_of_texts" value="1"/><property id="Potency" value=" "/><property id="Evaluation" value=" "/><property id="frequency" value="2"/><property id="relative_frequency-within_text" value="0.018867925"/><property id="gram_type" value="ngram"/></node><node id="techniques"><property id="Action" value=" "/><property id="number_of_texts" value="1"/><property id="Potency" value=" "/><property id="Evaluation" value=" "/><property id="frequency" value="4"/><property id="relative_frequency-within_text" value="0.03773585"/><property id="gram_type" value="single"/></node><node id="&#169;"><property id="Action" value=" "/><property id="number_of_texts" value="1"/><property id="Potency" value=" "/><property id="Evaluation" value=" "/><property id="frequency" value="1"/><property id="relative_frequency-within_text" value="0.009433962"/><property id="gram_type" value="single"/></node><node id="&#225;"><property id="Action" value=" "/><property id="number_of_texts" value="1"/><property id="Potency" value=" "/><property id="Evaluation" value=" "/><property id="frequency" value="1"/><property id="relative_frequency-within_text" value="0.009433962"/><property id="gram_type" value="single"/></node><node id="&#8226;"><property id="Action" value=" "/><property id="number_of_texts" value="1"/><property id="Potency" value=" "/><property id="Evaluation" value=" "/><property id="frequency" value="10"/><property id="relative_frequency-within_text" value="0.094339624"/><property id="gram_type" value="single"/></node><node id="&#64257;"><property id="Action" value=" "/><property id="number_of_texts" value="1"/><property id="Potency" value=" "/><property id="Evaluation" value=" "/><property id="frequency" value="88"/><property id="relative_frequency-within_text" value="0.8301887"/><property id="gram_type" value="single"/></node><node id="&#64257;-based"><property id="Action" value=" "/><property id="number_of_texts" value="1"/><property id="Potency" value=" "/><property id="Evaluation" value=" "/><property id="frequency" value="3"/><property id="relative_frequency-within_text" value="0.028301887"/><property id="gram_type" value="single"/></node><node id="&#64257;-intelligence"><property id="Action" value=" "/><property id="number_of_texts" value="1"/><property id="Potency" value=" "/><property id="Evaluation" value=" "/><property id="frequency" value="1"/><property id="relative_frequency-within_text" value="0.009433962"/><property id="gram_type" value="single"/></node><node id="&#64257;&#64257;&#64257;"><property id="Action" value=" "/><property id="number_of_texts" value="1"/><property id="Potency" value=" "/><property id="Evaluation" value=" "/><property id="frequency" value="1"/><property id="relative_frequency-within_text" value="0.009433962"/><property id="gram_type" value="single"/></node><node id="&#64258;"><property id="Action" value=" "/><property id="number_of_texts" value="1"/><property id="Potency" value=" "/><property id="Evaluation" value=" "/><property id="frequency" value="5"/><property id="relative_frequency-within_text" value="0.047169812"/><property id="gram_type" value="single"/></node></nodeclass><nodeclass type="Belief" id="Belief"><propertyIdentities><propertyIdentity id="Action" type="text" singleValued="false"/><propertyIdentity id="Evaluation" type="text" singleValued="false"/><propertyIdentity id="frequency" type="number" singleValued="false"/><propertyIdentity id="gram_type" type="categoryText" singleValued="false"/><propertyIdentity id="number_of_texts" type="text" singleValued="false"/><propertyIdentity id="Potency" type="text" singleValued="false"/><propertyIdentity id="relative_frequency-within_text" type="text" singleValued="false"/></propertyIdentities><node id="belief"><property id="gram_type" value="single"/><property id="frequency" value="5"/><property id="Evaluation" value=" "/><property id="number_of_texts" value="1"/><property id="Action" value=" "/><property id="Potency" value=" "/><property id="relative_frequency-within_text" value="0.047169812"/></node></nodeclass><nodeclass type="Resource" id="Resource"><propertyIdentities><propertyIdentity id="Action" type="text" singleValued="false"/><propertyIdentity id="Evaluation" type="text" singleValued="false"/><propertyIdentity id="frequency" type="number" singleValued="false"/><propertyIdentity id="gram_type" type="categoryText" singleValued="false"/><propertyIdentity id="number_of_texts" type="text" singleValued="false"/><propertyIdentity id="Potency" type="text" singleValued="false"/><propertyIdentity id="relative_frequency-within_text" type="text" singleValued="false"/></propertyIdentities><node id="resource"><property id="gram_type" value="single"/><property id="Potency" value=" "/><property id="frequency" value="1"/><property id="Evaluation" value=" "/><property id="number_of_texts" value="1"/><property id="Action" value=" "/><property id="relative_frequency-within_text" value="0.009433962"/></node></nodeclass></nodes><networks><network sourceType="Unknown" source="Unknown" targetType="Unknown" target="Unknown" id="Unknown x Unknown" isDirected="false" allowSelfLoops="false" isBinary="false"><propertyIdentities><propertyIdentity id="average distance" type="number" singleValued="false"/><propertyIdentity id="shortest distance" type="number" singleValued="false"/></propertyIdentities><link source="protection_effect" target="isolation_effect" value="2.0"><property id="average distance" value="1.0"/><property id="shortest distance" value="1.0"/></link><link source="protection_effect" target="certainty_effect" value="2.0"><property id="average distance" value="2.0"/><property id="shortest distance" value="2.0"/></link><link source="protection_effect" target="gain" value="2.0"><property id="average distance" value="1.0"/><property id="shortest distance" value="1.0"/></link><link source="protection_effect" target="intrinsic_rewards" value="2.0"><property id="average distance" value="1.0"/><property id="shortest distance" value="1.0"/></link><link source="protection_effect" target="participant_modeling" value="2.0"><property id="average distance" value="4.0"/><property id="shortest distance" value="4.0"/></link><link source="protection_effect" target="&#64257;" value="4.0"><property id="average distance" value="1.0"/><property id="shortest distance" value="1.0"/></link><link source="protection_effect" target="personality" value="2.0"><property id="average distance" value="2.0"/><property id="shortest distance" value="2.0"/></link><link source="protection_effect" target="behavior" value="2.0"><property id="average distance" value="1.0"/><property id="shortest distance" value="1.0"/></link><link source="protection_effect" target="perceived_vulnerability" value="2.0"><property id="average distance" value="1.0"/><property id="shortest distance" value="1.0"/></link><link source="protection_effect" target="loss" value="18.0"><property id="average distance" value="1.5555556"/><property id="shortest distance" value="1.5555556"/></link><link source="satisfaction_of_needs" target="behavior_control-ability" value="2.0"><property id="average distance" value="1.0"/><property id="shortest distance" value="1.0"/></link><link source="division" target="appraisal" value="2.0"><property id="average distance" value="1.0"/><property id="shortest distance" value="1.0"/></link><link source="division" target="learning" value="2.0"><property id="average distance" value="2.0"/><property id="shortest distance" value="2.0"/></link><link source="division" target="personality" value="2.0"><property id="average distance" value="1.0"/><property id="shortest distance" value="1.0"/></link><link source="division" target="loss" value="2.0"><property id="average distance" value="1.0"/><property id="shortest distance" value="1.0"/></link><link source="appraisal" target="evaluating" value="4.0"><property id="average distance" value="21.0"/><property id="shortest distance" value="21.0"/></link><link source="appraisal" target="certainty_effect" value="10.0"><property id="average distance" value="10.8"/><property id="shortest distance" value="10.8"/></link><link source="appraisal" target="division" value="2.0"><property id="average distance" value="1.0"/><property id="shortest distance" value="1.0"/></link><link source="appraisal" target="gain" value="4.0"><property id="average distance" value="2.0"/><property id="shortest distance" value="2.0"/></link><link source="appraisal" target="mental_calculation" value="2.0"><property id="average distance" value="1.0"/><property id="shortest distance" value="1.0"/></link><link source="appraisal" target="&#64257;" value="2.0"><property id="average distance" value="2.0"/><property id="shortest distance" value="2.0"/></link><link source="appraisal" target="judging" value="2.0"><property id="average distance" value="5.0"/><property id="shortest distance" value="5.0"/></link><link source="appraisal" target="personality" value="18.0"><property id="average distance" value="3.4444444"/><property id="shortest distance" value="3.4444444"/></link><link source="appraisal" target="behavior" value="2.0"><property id="average distance" value="1.0"/><property id="shortest distance" value="1.0"/></link><link source="appraisal" target="perceived_vulnerability" value="24.0"><property id="average distance" value="10.25"/><property id="shortest distance" value="10.25"/></link><link source="appraisal" target="social_circumstance" value="2.0"><property id="average distance" value="6.0"/><property id="shortest distance" value="6.0"/></link><link source="appraisal" target="loss" value="4.0"><property id="average distance" value="22.0"/><property id="shortest distance" value="22.0"/></link><link source="perception" target="focus" value="2.0"><property id="average distance" value="1.0"/><property id="shortest distance" value="1.0"/></link><link source="perception" target="certainty_effect" value="2.0"><property id="average distance" value="2.0"/><property id="shortest distance" value="2.0"/></link><link source="perception" target="intrinsic_rewards" value="2.0"><property id="average distance" value="1.0"/><property id="shortest distance" value="1.0"/></link><link source="perception" target="mental_calculation" value="2.0"><property id="average distance" value="3.0"/><property id="shortest distance" value="3.0"/></link><link source="perception" target="&#64257;" value="4.0"><property id="average distance" value="1.5"/><property id="shortest distance" value="1.5"/></link><link source="perception" target="perceived_vulnerability" value="4.0"><property id="average distance" value="2.0"/><property id="shortest distance" value="2.0"/></link><link source="perception" target="loss" value="10.0"><property id="average distance" value="3.0"/><property id="shortest distance" value="3.0"/></link><link source="learning" target="division" value="2.0"><property id="average distance" value="2.0"/><property id="shortest distance" value="2.0"/></link><link source="learning" target="&#64257;" value="4.0"><property id="average distance" value="1.0"/><property id="shortest distance" value="1.0"/></link><link source="learning" target="personality" value="2.0"><property id="average distance" value="3.0"/><property id="shortest distance" value="3.0"/></link><link source="learning" target="loss" value="2.0"><property id="average distance" value="1.0"/><property id="shortest distance" value="1.0"/></link><link source="intentionality" target="syllogistic_rules" value="2.0"><property id="average distance" value="1.0"/><property id="shortest distance" value="1.0"/></link><link source="intentionality" target="mental_calculation" value="2.0"><property id="average distance" value="1.0"/><property id="shortest distance" value="1.0"/></link><link source="intentionality" target="&#64257;" value="2.0"><property id="average distance" value="1.0"/><property id="shortest distance" value="1.0"/></link><link source="mental_calculation" target="behavior_control-ability" value="2.0"><property id="average distance" value="4.0"/><property id="shortest distance" value="4.0"/></link><link source="mental_calculation" target="certainty_effect" value="2.0"><property id="average distance" value="1.0"/><property id="shortest distance" value="1.0"/></link><link source="mental_calculation" target="syllogistic_rules" value="4.0"><property id="average distance" value="2.5"/><property id="shortest distance" value="2.5"/></link><link source="mental_calculation" target="gain" value="2.0"><property id="average distance" value="1.0"/><property id="shortest distance" value="1.0"/></link><link source="mental_calculation" target="appraisal" value="2.0"><property id="average distance" value="1.0"/><property id="shortest distance" value="1.0"/></link><link source="mental_calculation" target="intentionality" value="2.0"><property id="average distance" value="1.0"/><property id="shortest distance" value="1.0"/></link><link source="mental_calculation" target="perception" value="2.0"><property id="average distance" value="3.0"/><property id="shortest distance" value="3.0"/></link><link source="mental_calculation" target="&#64257;" value="4.0"><property id="average distance" value="1.0"/><property id="shortest distance" value="1.0"/></link><link source="mental_calculation" target="goal" value="2.0"><property id="average distance" value="1.0"/><property id="shortest distance" value="1.0"/></link><link source="mental_calculation" target="personality" value="10.0"><property id="average distance" value="1.2"/><property id="shortest distance" value="1.2"/></link><link source="mental_calculation" target="perceived_vulnerability" value="6.0"><property id="average distance" value="3.3333333"/><property id="shortest distance" value="3.3333333"/></link><link source="mental_calculation" target="loss" value="10.0"><property id="average distance" value="2.8"/><property id="shortest distance" value="2.8"/></link><link source="&#64257;" target="protection_effect" value="4.0"><property id="average distance" value="1.0"/><property id="shortest distance" value="1.0"/></link><link source="&#64257;" target="appraisal" value="2.0"><property id="average distance" value="2.0"/><property id="shortest distance" value="2.0"/></link><link source="&#64257;" target="intentionality" value="2.0"><property id="average distance" value="1.0"/><property id="shortest distance" value="1.0"/></link><link source="&#64257;" target="learning" value="4.0"><property id="average distance" value="1.0"/><property id="shortest distance" value="1.0"/></link><link source="&#64257;" target="perception" value="4.0"><property id="average distance" value="1.5"/><property id="shortest distance" value="1.5"/></link><link source="&#64257;" target="mental_calculation" value="4.0"><property id="average distance" value="1.0"/><property id="shortest distance" value="1.0"/></link><link source="&#64257;" target="perceived_vulnerability" value="22.0"><property id="average distance" value="2.0"/><property id="shortest distance" value="2.0"/></link><link source="&#64257;" target="history" value="2.0"><property id="average distance" value="1.0"/><property id="shortest distance" value="1.0"/></link><link source="&#64257;" target="techniques" value="2.0"><property id="average distance" value="2.0"/><property id="shortest distance" value="2.0"/></link><link source="&#64257;" target="simplifying" value="2.0"><property id="average distance" value="2.0"/><property id="shortest distance" value="2.0"/></link><link source="&#64257;" target="evaluating" value="8.0"><property id="average distance" value="2.25"/><property id="shortest distance" value="2.25"/></link><link source="&#64257;" target="behavior_control-ability" value="2.0"><property id="average distance" value="1.0"/><property id="shortest distance" value="1.0"/></link><link source="&#64257;" target="focus" value="14.0"><property id="average distance" value="1.2857143"/><property id="shortest distance" value="1.2857143"/></link><link source="&#64257;" target="certainty_effect" value="6.0"><property id="average distance" value="1.0"/><property id="shortest distance" value="1.0"/></link><link source="&#64257;" target="function" value="4.0"><property id="average distance" value="1.0"/><property id="shortest distance" value="1.0"/></link><link source="&#64257;" target="process" value="4.0"><property id="average distance" value="3.5"/><property id="shortest distance" value="3.5"/></link><link source="&#64257;" target="intrinsic_rewards" value="24.0"><property id="average distance" value="1.5"/><property id="shortest distance" value="1.5"/></link><link source="&#64257;" target="participant_modeling" value="8.0"><property id="average distance" value="1.25"/><property id="shortest distance" value="1.25"/></link><link source="&#64257;" target="behavior" value="14.0"><property id="average distance" value="1.4285715"/><property id="shortest distance" value="1.4285715"/></link><link source="&#64257;" target="&#64257;-based" value="2.0"><property id="average distance" value="1.0"/><property id="shortest distance" value="1.0"/></link><link source="&#64257;" target="possibility_effect" value="4.0"><property id="average distance" value="1.5"/><property id="shortest distance" value="1.5"/></link><link source="&#64257;" target="perceived_consensus" value="2.0"><property id="average distance" value="3.0"/><property id="shortest distance" value="3.0"/></link><link source="&#64257;" target="combining" value="6.0"><property id="average distance" value="2.0"/><property id="shortest distance" value="2.0"/></link><link source="&#64257;" target="comply_effect" value="8.0"><property id="average distance" value="1.75"/><property id="shortest distance" value="1.75"/></link><link source="&#64257;" target="segregating" value="4.0"><property id="average distance" value="1.5"/><property id="shortest distance" value="1.5"/></link><link source="&#64257;" target="judging" value="4.0"><property id="average distance" value="1.0"/><property id="shortest distance" value="1.0"/></link><link source="&#64257;" target="loss" value="40.0"><property id="average distance" value="1.9"/><property id="shortest distance" value="1.9"/></link><link source="&#64257;" target="physical_quality" value="2.0"><property id="average distance" value="3.0"/><property id="shortest distance" value="3.0"/></link><link source="&#64257;" target="&#64258;" value="4.0"><property id="average distance" value="1.25"/><property id="shortest distance" value="1.5"/></link><link source="&#64257;" target="personality" value="36.0"><property id="average distance" value="1.6666666"/><property id="shortest distance" value="1.6666666"/></link><link source="perceived_vulnerability" target="combining" value="4.0"><property id="average distance" value="1.0"/><property id="shortest distance" value="1.0"/></link><link source="perceived_vulnerability" target="isolation_effect" value="2.0"><property id="average distance" value="1.0"/><property id="shortest distance" value="1.0"/></link><link source="perceived_vulnerability" target="protection_effect" value="2.0"><property id="average distance" value="1.0"/><property id="shortest distance" value="1.0"/></link><link source="perceived_vulnerability" target="appraisal" value="24.0"><property id="average distance" value="10.25"/><property id="shortest distance" value="10.25"/></link><link source="perceived_vulnerability" target="perception" value="4.0"><property id="average distance" value="2.0"/><property id="shortest distance" value="2.0"/></link><link source="perceived_vulnerability" target="mental_calculation" value="6.0"><property id="average distance" value="3.3333333"/><property id="shortest distance" value="3.3333333"/></link><link source="perceived_vulnerability" target="&#64257;" value="22.0"><property id="average distance" value="2.0"/><property id="shortest distance" value="2.0"/></link><link source="perceived_vulnerability" target="judging" value="28.0"><property id="average distance" value="13.357142"/><property id="shortest distance" value="13.357142"/></link><link source="perceived_vulnerability" target="persistence" value="2.0"><property id="average distance" value="1.0"/><property id="shortest distance" value="1.0"/></link><link source="perceived_vulnerability" target="social_circumstance" value="24.0"><property id="average distance" value="16.25"/><property id="shortest distance" value="16.25"/></link><link source="perceived_vulnerability" target="loss" value="106.0"><property id="average distance" value="6.3773584"/><property id="shortest distance" value="6.3773584"/></link><link source="perceived_vulnerability" target="simplifying" value="4.0"><property id="average distance" value="1.5"/><property id="shortest distance" value="1.5"/></link><link source="perceived_vulnerability" target="evaluating" value="52.0"><property id="average distance" value="10.115385"/><property id="shortest distance" value="10.115385"/></link><link source="perceived_vulnerability" target="behavior_control-ability" value="10.0"><property id="average distance" value="1.4"/><property id="shortest distance" value="1.4"/></link><link source="perceived_vulnerability" target="focus" value="2.0"><property id="average distance" value="2.0"/><property id="shortest distance" value="2.0"/></link><link source="perceived_vulnerability" target="certainty_effect" value="168.0"><property id="average distance" value="4.678571"/><property id="shortest distance" value="4.678571"/></link><link source="perceived_vulnerability" target="function" value="2.0"><property id="average distance" value="2.0"/><property id="shortest distance" value="2.0"/></link><link source="perceived_vulnerability" target="gain" value="30.0"><property id="average distance" value="10.0"/><property id="shortest distance" value="10.0"/></link><link source="perceived_vulnerability" target="intrinsic_rewards" value="2.0"><property id="average distance" value="3.0"/><property id="shortest distance" value="3.0"/></link><link source="perceived_vulnerability" target="participant_modeling" value="6.0"><property id="average distance" value="1.0"/><property id="shortest distance" value="1.0"/></link><link source="perceived_vulnerability" target="personality" value="174.0"><property id="average distance" value="9.873563"/><property id="shortest distance" value="9.873563"/></link><link source="perceived_vulnerability" target="behavior" value="2.0"><property id="average distance" value="1.0"/><property id="shortest distance" value="1.0"/></link><link source="perceived_vulnerability" target="perceived_responsibility" value="2.0"><property id="average distance" value="1.0"/><property id="shortest distance" value="1.0"/></link><link source="perceived_vulnerability" target="possibility_effect" value="2.0"><property id="average distance" value="1.0"/><property id="shortest distance" value="1.0"/></link><link source="social_circumstance" target="evaluating" value="4.0"><property id="average distance" value="27.0"/><property id="shortest distance" value="27.0"/></link><link source="social_circumstance" target="certainty_effect" value="10.0"><property id="average distance" value="16.8"/><property id="shortest distance" value="16.8"/></link><link source="social_circumstance" target="gain" value="2.0"><property id="average distance" value="4.0"/><property id="shortest distance" value="4.0"/></link><link source="social_circumstance" target="appraisal" value="2.0"><property id="average distance" value="6.0"/><property id="shortest distance" value="6.0"/></link><link source="social_circumstance" target="judging" value="2.0"><property id="average distance" value="1.0"/><property id="shortest distance" value="1.0"/></link><link source="social_circumstance" target="personality" value="12.0"><property id="average distance" value="6.0"/><property id="shortest distance" value="6.0"/></link><link source="social_circumstance" target="perceived_vulnerability" value="24.0"><property id="average distance" value="16.25"/><property id="shortest distance" value="16.25"/></link><link source="social_circumstance" target="loss" value="4.0"><property id="average distance" value="28.0"/><property id="shortest distance" value="28.0"/></link><link source="history" target="combining" value="2.0"><property id="average distance" value="1.0"/><property id="shortest distance" value="1.0"/></link><link source="history" target="&#64257;" value="2.0"><property id="average distance" value="1.0"/><property id="shortest distance" value="1.0"/></link><link source="history" target="&#64257;-based" value="2.0"><property id="average distance" value="2.0"/><property id="shortest distance" value="2.0"/></link><link source="history" target="techniques" value="2.0"><property id="average distance" value="3.0"/><property id="shortest distance" value="3.0"/></link><link source="history" target="experiential_awareness" value="2.0"><property id="average distance" value="2.0"/><property id="shortest distance" value="2.0"/></link><link source="techniques" target="&#64257;" value="2.0"><property id="average distance" value="2.0"/><property id="shortest distance" value="2.0"/></link><link source="techniques" target="&#64257;-based" value="2.0"><property id="average distance" value="1.0"/><property id="shortest distance" value="1.0"/></link><link source="techniques" target="history" value="2.0"><property id="average distance" value="3.0"/><property id="shortest distance" value="3.0"/></link><link source="simplifying" target="evaluating" value="2.0"><property id="average distance" value="1.0"/><property id="shortest distance" value="1.0"/></link><link source="simplifying" target="certainty_effect" value="2.0"><property id="average distance" value="1.0"/><property id="shortest distance" value="1.0"/></link><link source="simplifying" target="&#64257;" value="2.0"><property id="average distance" value="2.0"/><property id="shortest distance" value="2.0"/></link><link source="simplifying" target="personality" value="6.0"><property id="average distance" value="1.0"/><property id="shortest distance" value="1.0"/></link><link source="simplifying" target="behavior" value="2.0"><property id="average distance" value="1.0"/><property id="shortest distance" value="1.0"/></link><link source="simplifying" target="perceived_vulnerability" value="4.0"><property id="average distance" value="1.5"/><property id="shortest distance" value="1.5"/></link><link source="evaluating" target="simplifying" value="2.0"><property id="average distance" value="1.0"/><property id="shortest distance" value="1.0"/></link><link source="evaluating" target="combining" value="2.0"><property id="average distance" value="1.0"/><property id="shortest distance" value="1.0"/></link><link source="evaluating" target="certainty_effect" value="24.0"><property id="average distance" value="8.75"/><property id="shortest distance" value="8.75"/></link><link source="evaluating" target="gain" value="4.0"><property id="average distance" value="23.0"/><property id="shortest distance" value="23.0"/></link><link source="evaluating" target="appraisal" value="4.0"><property id="average distance" value="21.0"/><property id="shortest distance" value="21.0"/></link><link source="evaluating" target="&#64257;" value="8.0"><property id="average distance" value="2.25"/><property id="shortest distance" value="2.25"/></link><link source="evaluating" target="judging" value="4.0"><property id="average distance" value="26.0"/><property id="shortest distance" value="26.0"/></link><link source="evaluating" target="personality" value="32.0"><property id="average distance" value="16.6875"/><property id="shortest distance" value="16.6875"/></link><link source="evaluating" target="perceived_vulnerability" value="52.0"><property id="average distance" value="10.115385"/><property id="shortest distance" value="10.115385"/></link><link source="evaluating" target="social_circumstance" value="4.0"><property id="average distance" value="27.0"/><property id="shortest distance" value="27.0"/></link><link source="evaluating" target="loss" value="48.0"><property id="average distance" value="1.9166666"/><property id="shortest distance" value="1.9166666"/></link><link source="behavior_control-ability" target="certainty_effect" value="2.0"><property id="average distance" value="3.0"/><property id="shortest distance" value="3.0"/></link><link source="behavior_control-ability" target="satisfaction_of_needs" value="2.0"><property id="average distance" value="1.0"/><property id="shortest distance" value="1.0"/></link><link source="behavior_control-ability" target="mental_calculation" value="2.0"><property id="average distance" value="4.0"/><property id="shortest distance" value="4.0"/></link><link source="behavior_control-ability" target="&#64257;" value="2.0"><property id="average distance" value="1.0"/><property id="shortest distance" value="1.0"/></link><link source="behavior_control-ability" target="perceived_vulnerability" value="10.0"><property id="average distance" value="1.4"/><property id="shortest distance" value="1.4"/></link><link source="behavior_control-ability" target="loss" value="2.0"><property id="average distance" value="2.0"/><property id="shortest distance" value="2.0"/></link><link source="focus" target="&#64258;" value="2.0"><property id="average distance" value="1.0"/><property id="shortest distance" value="1.0"/></link><link source="focus" target="intrinsic_rewards" value="4.0"><property id="average distance" value="1.0"/><property id="shortest distance" value="1.0"/></link><link source="focus" target="perception" value="2.0"><property id="average distance" value="1.0"/><property id="shortest distance" value="1.0"/></link><link source="focus" target="&#64257;" value="14.0"><property id="average distance" value="1.2857143"/><property id="shortest distance" value="1.2857143"/></link><link source="focus" target="perceived_vulnerability" value="2.0"><property id="average distance" value="2.0"/><property id="shortest distance" value="2.0"/></link><link source="focus" target="experiential_awareness" value="2.0"><property id="average distance" value="1.0"/><property id="shortest distance" value="1.0"/></link><link source="focus" target="possibility_effect" value="2.0"><property id="average distance" value="1.0"/><property id="shortest distance" value="1.0"/></link><link source="&#64257;-intelligence" target="planning" value="2.0"><property id="average distance" value="1.0"/><property id="shortest distance" value="1.0"/></link><link source="certainty_effect" target="protection_effect" value="2.0"><property id="average distance" value="2.0"/><property id="shortest distance" value="2.0"/></link><link source="certainty_effect" target="appraisal" value="10.0"><property id="average distance" value="10.8"/><property id="shortest distance" value="10.8"/></link><link source="certainty_effect" target="perception" value="2.0"><property id="average distance" value="2.0"/><property id="shortest distance" value="2.0"/></link><link source="certainty_effect" target="mental_calculation" value="2.0"><property id="average distance" value="1.0"/><property id="shortest distance" value="1.0"/></link><link source="certainty_effect" target="&#64257;" value="6.0"><property id="average distance" value="1.0"/><property id="shortest distance" value="1.0"/></link><link source="certainty_effect" target="judging" value="12.0"><property id="average distance" value="13.5"/><property id="shortest distance" value="13.5"/></link><link source="certainty_effect" target="persistence" value="2.0"><property id="average distance" value="2.0"/><property id="shortest distance" value="2.0"/></link><link source="certainty_effect" target="perceived_vulnerability" value="168.0"><property id="average distance" value="4.678571"/><property id="shortest distance" value="4.678571"/></link><link source="certainty_effect" target="social_circumstance" value="10.0"><property id="average distance" value="16.8"/><property id="shortest distance" value="16.8"/></link><link source="certainty_effect" target="loss" value="30.0"><property id="average distance" value="8.6"/><property id="shortest distance" value="8.6"/></link><link source="certainty_effect" target="simplifying" value="2.0"><property id="average distance" value="1.0"/><property id="shortest distance" value="1.0"/></link><link source="certainty_effect" target="evaluating" value="24.0"><property id="average distance" value="8.75"/><property id="shortest distance" value="8.75"/></link><link source="certainty_effect" target="behavior_control-ability" value="2.0"><property id="average distance" value="3.0"/><property id="shortest distance" value="3.0"/></link><link source="certainty_effect" target="gain" value="10.0"><property id="average distance" value="12.8"/><property id="shortest distance" value="12.8"/></link><link source="certainty_effect" target="personality" value="68.0"><property id="average distance" value="10.411765"/><property id="shortest distance" value="10.411765"/></link><link source="function" target="combining" value="2.0"><property id="average distance" value="2.0"/><property id="shortest distance" value="2.0"/></link><link source="function" target="generalizing" value="2.0"><property id="average distance" value="1.0"/><property id="shortest distance" value="1.0"/></link><link source="function" target="gain" value="2.0"><property id="average distance" value="1.0"/><property id="shortest distance" value="1.0"/></link><link source="function" target="process" value="2.0"><property id="average distance" value="1.0"/><property id="shortest distance" value="1.0"/></link><link source="function" target="&#64257;" value="4.0"><property id="average distance" value="1.0"/><property id="shortest distance" value="1.0"/></link><link source="function" target="personality" value="8.0"><property id="average distance" value="1.25"/><property id="shortest distance" value="1.25"/></link><link source="function" target="extrinsic_rewards" value="4.0"><property id="average distance" value="1.0"/><property id="shortest distance" value="1.0"/></link><link source="function" target="perceived_vulnerability" value="2.0"><property id="average distance" value="2.0"/><property id="shortest distance" value="2.0"/></link><link source="function" target="loss" value="4.0"><property id="average distance" value="1.5"/><property id="shortest distance" value="1.5"/></link><link source="process" target="combining" value="2.0"><property id="average distance" value="1.0"/><property id="shortest distance" value="1.0"/></link><link source="process" target="function" value="2.0"><property id="average distance" value="1.0"/><property id="shortest distance" value="1.0"/></link><link source="process" target="&#64257;" value="4.0"><property id="average distance" value="3.5"/><property id="shortest distance" value="3.5"/></link><link source="process" target="personality" value="10.0"><property id="average distance" value="2.2"/><property id="shortest distance" value="2.2"/></link><link source="process" target="loss" value="4.0"><property id="average distance" value="1.5"/><property id="shortest distance" value="1.5"/></link><link source="intrinsic_rewards" target="physical_quality" value="2.0"><property id="average distance" value="2.0"/><property id="shortest distance" value="2.0"/></link><link source="intrinsic_rewards" target="protection_effect" value="2.0"><property id="average distance" value="1.0"/><property id="shortest distance" value="1.0"/></link><link source="intrinsic_rewards" target="focus" value="4.0"><property id="average distance" value="1.0"/><property id="shortest distance" value="1.0"/></link><link source="intrinsic_rewards" target="perception" value="2.0"><property id="average distance" value="1.0"/><property id="shortest distance" value="1.0"/></link><link source="intrinsic_rewards" target="&#64257;" value="24.0"><property id="average distance" value="1.5"/><property id="shortest distance" value="1.5"/></link><link source="intrinsic_rewards" target="personality" value="2.0"><property id="average distance" value="1.0"/><property id="shortest distance" value="1.0"/></link><link source="intrinsic_rewards" target="behavior" value="2.0"><property id="average distance" value="1.0"/><property id="shortest distance" value="1.0"/></link><link source="intrinsic_rewards" target="perceived_vulnerability" value="2.0"><property id="average distance" value="3.0"/><property id="shortest distance" value="3.0"/></link><link source="intrinsic_rewards" target="&#64257;-based" value="4.0"><property id="average distance" value="1.0"/><property id="shortest distance" value="1.0"/></link><link source="intrinsic_rewards" target="possibility_effect" value="2.0"><property id="average distance" value="1.0"/><property id="shortest distance" value="1.0"/></link><link source="participant_modeling" target="isolation_effect" value="4.0"><property id="average distance" value="1.0"/><property id="shortest distance" value="1.0"/></link><link source="participant_modeling" target="protection_effect" value="2.0"><property id="average distance" value="4.0"/><property id="shortest distance" value="4.0"/></link><link source="participant_modeling" target="&#64258;" value="2.0"><property id="average distance" value="2.0"/><property id="shortest distance" value="2.0"/></link><link source="participant_modeling" target="comply_effect" value="2.0"><property id="average distance" value="3.0"/><property id="shortest distance" value="3.0"/></link><link source="participant_modeling" target="&#64257;" value="8.0"><property id="average distance" value="1.25"/><property id="shortest distance" value="1.25"/></link><link source="participant_modeling" target="personality" value="16.0"><property id="average distance" value="1.625"/><property id="shortest distance" value="1.625"/></link><link source="participant_modeling" target="perceived_vulnerability" value="6.0"><property id="average distance" value="1.0"/><property id="shortest distance" value="1.0"/></link><link source="participant_modeling" target="loss" value="12.0"><property id="average distance" value="1.8333334"/><property id="shortest distance" value="1.8333334"/></link><link source="participant_modeling" target="possibility_effect" value="4.0"><property id="average distance" value="2.5"/><property id="shortest distance" value="2.5"/></link><link source="goal" target="mental_calculation" value="2.0"><property id="average distance" value="1.0"/><property id="shortest distance" value="1.0"/></link><link source="goal" target="personality" value="2.0"><property id="average distance" value="2.0"/><property id="shortest distance" value="2.0"/></link><link source="behavior" target="simplifying" value="2.0"><property id="average distance" value="1.0"/><property id="shortest distance" value="1.0"/></link><link source="behavior" target="protection_effect" value="2.0"><property id="average distance" value="1.0"/><property id="shortest distance" value="1.0"/></link><link source="behavior" target="gain" value="6.0"><property id="average distance" value="1.3333334"/><property id="shortest distance" value="1.3333334"/></link><link source="behavior" target="intrinsic_rewards" value="2.0"><property id="average distance" value="1.0"/><property id="shortest distance" value="1.0"/></link><link source="behavior" target="appraisal" value="2.0"><property id="average distance" value="1.0"/><property id="shortest distance" value="1.0"/></link><link source="behavior" target="segregating" value="2.0"><property id="average distance" value="1.0"/><property id="shortest distance" value="1.0"/></link><link source="behavior" target="&#64257;" value="14.0"><property id="average distance" value="1.4285715"/><property id="shortest distance" value="1.4285715"/></link><link source="behavior" target="judging" value="2.0"><property id="average distance" value="1.0"/><property id="shortest distance" value="1.0"/></link><link source="behavior" target="personality" value="6.0"><property id="average distance" value="1.6666666"/><property id="shortest distance" value="1.6666666"/></link><link source="behavior" target="perceived_vulnerability" value="2.0"><property id="average distance" value="1.0"/><property id="shortest distance" value="1.0"/></link><link source="extrinsic_rewards" target="function" value="4.0"><property id="average distance" value="1.0"/><property id="shortest distance" value="1.0"/></link><link source="extrinsic_rewards" target="loss" value="4.0"><property id="average distance" value="2.0"/><property id="shortest distance" value="2.0"/></link><link source="&#64257;-based" target="intrinsic_rewards" value="4.0"><property id="average distance" value="1.0"/><property id="shortest distance" value="1.0"/></link><link source="&#64257;-based" target="&#64257;" value="2.0"><property id="average distance" value="1.0"/><property id="shortest distance" value="1.0"/></link><link source="&#64257;-based" target="history" value="2.0"><property id="average distance" value="2.0"/><property id="shortest distance" value="2.0"/></link><link source="&#64257;-based" target="techniques" value="2.0"><property id="average distance" value="1.0"/><property id="shortest distance" value="1.0"/></link><link source="perceived_responsibility" target="perceived_vulnerability" value="2.0"><property id="average distance" value="1.0"/><property id="shortest distance" value="1.0"/></link><link source="experiential_awareness" target="combining" value="2.0"><property id="average distance" value="1.0"/><property id="shortest distance" value="1.0"/></link><link source="experiential_awareness" target="focus" value="2.0"><property id="average distance" value="1.0"/><property id="shortest distance" value="1.0"/></link><link source="experiential_awareness" target="history" value="2.0"><property id="average distance" value="2.0"/><property id="shortest distance" value="2.0"/></link><link source="possibility_effect" target="physical_quality" value="2.0"><property id="average distance" value="1.0"/><property id="shortest distance" value="1.0"/></link><link source="possibility_effect" target="internalization" value="2.0"><property id="average distance" value="1.0"/><property id="shortest distance" value="1.0"/></link><link source="possibility_effect" target="&#64258;" value="2.0"><property id="average distance" value="1.0"/><property id="shortest distance" value="1.0"/></link><link source="possibility_effect" target="focus" value="2.0"><property id="average distance" value="1.0"/><property id="shortest distance" value="1.0"/></link><link source="possibility_effect" target="intrinsic_rewards" value="2.0"><property id="average distance" value="1.0"/><property id="shortest distance" value="1.0"/></link><link source="possibility_effect" target="participant_modeling" value="4.0"><property id="average distance" value="2.5"/><property id="shortest distance" value="2.5"/></link><link source="possibility_effect" target="&#64257;" value="4.0"><property id="average distance" value="1.5"/><property id="shortest distance" value="1.5"/></link><link source="possibility_effect" target="persistence" value="2.0"><property id="average distance" value="1.0"/><property id="shortest distance" value="1.0"/></link><link source="possibility_effect" target="personality" value="6.0"><property id="average distance" value="1.3333334"/><property id="shortest distance" value="1.3333334"/></link><link source="possibility_effect" target="perceived_vulnerability" value="2.0"><property id="average distance" value="1.0"/><property id="shortest distance" value="1.0"/></link><link source="possibility_effect" target="loss" value="6.0"><property id="average distance" value="2.0"/><property id="shortest distance" value="2.0"/></link><link source="perceived_consensus" target="&#64257;" value="2.0"><property id="average distance" value="3.0"/><property id="shortest distance" value="3.0"/></link><link source="perceived_consensus" target="loss" value="4.0"><property id="average distance" value="1.5"/><property id="shortest distance" value="1.5"/></link><link source="combining" target="evaluating" value="2.0"><property id="average distance" value="1.0"/><property id="shortest distance" value="1.0"/></link><link source="combining" target="function" value="2.0"><property id="average distance" value="2.0"/><property id="shortest distance" value="2.0"/></link><link source="combining" target="process" value="2.0"><property id="average distance" value="1.0"/><property id="shortest distance" value="1.0"/></link><link source="combining" target="&#64257;" value="6.0"><property id="average distance" value="2.0"/><property id="shortest distance" value="2.0"/></link><link source="combining" target="personality" value="4.0"><property id="average distance" value="1.5"/><property id="shortest distance" value="1.5"/></link><link source="combining" target="perceived_vulnerability" value="4.0"><property id="average distance" value="1.0"/><property id="shortest distance" value="1.0"/></link><link source="combining" target="history" value="2.0"><property id="average distance" value="1.0"/><property id="shortest distance" value="1.0"/></link><link source="combining" target="experiential_awareness" value="2.0"><property id="average distance" value="1.0"/><property id="shortest distance" value="1.0"/></link><link source="combining" target="loss" value="12.0"><property id="average distance" value="1.3333334"/><property id="shortest distance" value="1.3333334"/></link><link source="isolation_effect" target="protection_effect" value="2.0"><property id="average distance" value="1.0"/><property id="shortest distance" value="1.0"/></link><link source="isolation_effect" target="comply_effect" value="2.0"><property id="average distance" value="2.0"/><property id="shortest distance" value="2.0"/></link><link source="isolation_effect" target="participant_modeling" value="4.0"><property id="average distance" value="1.0"/><property id="shortest distance" value="1.0"/></link><link source="isolation_effect" target="personality" value="12.0"><property id="average distance" value="1.3333334"/><property id="shortest distance" value="1.3333334"/></link><link source="isolation_effect" target="perceived_vulnerability" value="2.0"><property id="average distance" value="1.0"/><property id="shortest distance" value="1.0"/></link><link source="isolation_effect" target="loss" value="8.0"><property id="average distance" value="2.5"/><property id="shortest distance" value="2.5"/></link><link source="comply_effect" target="isolation_effect" value="2.0"><property id="average distance" value="2.0"/><property id="shortest distance" value="2.0"/></link><link source="comply_effect" target="gain" value="2.0"><property id="average distance" value="1.0"/><property id="shortest distance" value="1.0"/></link><link source="comply_effect" target="participant_modeling" value="2.0"><property id="average distance" value="3.0"/><property id="shortest distance" value="3.0"/></link><link source="comply_effect" target="&#64257;" value="8.0"><property id="average distance" value="1.75"/><property id="shortest distance" value="1.75"/></link><link source="comply_effect" target="personality" value="12.0"><property id="average distance" value="1.5"/><property id="shortest distance" value="1.5"/></link><link source="comply_effect" target="loss" value="4.0"><property id="average distance" value="2.5"/><property id="shortest distance" value="2.5"/></link><link source="planning" target="&#64257;-intelligence" value="2.0"><property id="average distance" value="1.0"/><property id="shortest distance" value="1.0"/></link><link source="segregating" target="&#64257;" value="4.0"><property id="average distance" value="1.5"/><property id="shortest distance" value="1.5"/></link><link source="segregating" target="personality" value="4.0"><property id="average distance" value="2.5"/><property id="shortest distance" value="2.5"/></link><link source="segregating" target="behavior" value="2.0"><property id="average distance" value="1.0"/><property id="shortest distance" value="1.0"/></link><link source="judging" target="evaluating" value="4.0"><property id="average distance" value="26.0"/><property id="shortest distance" value="26.0"/></link><link source="judging" target="certainty_effect" value="12.0"><property id="average distance" value="13.5"/><property id="shortest distance" value="13.5"/></link><link source="judging" target="gain" value="4.0"><property id="average distance" value="2.0"/><property id="shortest distance" value="2.0"/></link><link source="judging" target="appraisal" value="2.0"><property id="average distance" value="5.0"/><property id="shortest distance" value="5.0"/></link><link source="judging" target="&#64257;" value="4.0"><property id="average distance" value="1.0"/><property id="shortest distance" value="1.0"/></link><link source="judging" target="personality" value="16.0"><property id="average distance" value="4.625"/><property id="shortest distance" value="4.625"/></link><link source="judging" target="behavior" value="2.0"><property id="average distance" value="1.0"/><property id="shortest distance" value="1.0"/></link><link source="judging" target="perceived_vulnerability" value="28.0"><property id="average distance" value="13.357142"/><property id="shortest distance" value="13.357142"/></link><link source="judging" target="social_circumstance" value="2.0"><property id="average distance" value="1.0"/><property id="shortest distance" value="1.0"/></link><link source="judging" target="loss" value="10.0"><property id="average distance" value="12.0"/><property id="shortest distance" value="12.0"/></link><link source="persistence" target="certainty_effect" value="2.0"><property id="average distance" value="2.0"/><property id="shortest distance" value="2.0"/></link><link source="persistence" target="perceived_vulnerability" value="2.0"><property id="average distance" value="1.0"/><property id="shortest distance" value="1.0"/></link><link source="persistence" target="possibility_effect" value="2.0"><property id="average distance" value="1.0"/><property id="shortest distance" value="1.0"/></link><link source="loss" target="protection_effect" value="18.0"><property id="average distance" value="1.5555556"/><property id="shortest distance" value="1.5555556"/></link><link source="loss" target="division" value="2.0"><property id="average distance" value="1.0"/><property id="shortest distance" value="1.0"/></link><link source="loss" target="appraisal" value="4.0"><property id="average distance" value="22.0"/><property id="shortest distance" value="22.0"/></link><link source="loss" target="learning" value="2.0"><property id="average distance" value="1.0"/><property id="shortest distance" value="1.0"/></link><link source="loss" target="perception" value="10.0"><property id="average distance" value="3.0"/><property id="shortest distance" value="3.0"/></link><link source="loss" target="mental_calculation" value="10.0"><property id="average distance" value="2.8"/><property id="shortest distance" value="2.8"/></link><link source="loss" target="&#64257;" value="40.0"><property id="average distance" value="1.9"/><property id="shortest distance" value="1.9"/></link><link source="loss" target="perceived_vulnerability" value="106.0"><property id="average distance" value="6.3773584"/><property id="shortest distance" value="6.3773584"/></link><link source="loss" target="social_circumstance" value="4.0"><property id="average distance" value="28.0"/><property id="shortest distance" value="28.0"/></link><link source="loss" target="evaluating" value="48.0"><property id="average distance" value="1.9166666"/><property id="shortest distance" value="1.9166666"/></link><link source="loss" target="behavior_control-ability" value="2.0"><property id="average distance" value="2.0"/><property id="shortest distance" value="2.0"/></link><link source="loss" target="certainty_effect" value="30.0"><property id="average distance" value="8.6"/><property id="shortest distance" value="8.6"/></link><link source="loss" target="function" value="4.0"><property id="average distance" value="1.5"/><property id="shortest distance" value="1.5"/></link><link source="loss" target="process" value="4.0"><property id="average distance" value="1.5"/><property id="shortest distance" value="1.5"/></link><link source="loss" target="participant_modeling" value="12.0"><property id="average distance" value="1.8333334"/><property id="shortest distance" value="1.8333334"/></link><link source="loss" target="extrinsic_rewards" value="4.0"><property id="average distance" value="2.0"/><property id="shortest distance" value="2.0"/></link><link source="loss" target="possibility_effect" value="6.0"><property id="average distance" value="2.0"/><property id="shortest distance" value="2.0"/></link><link source="loss" target="perceived_consensus" value="4.0"><property id="average distance" value="1.5"/><property id="shortest distance" value="1.5"/></link><link source="loss" target="combining" value="12.0"><property id="average distance" value="1.3333334"/><property id="shortest distance" value="1.3333334"/></link><link source="loss" target="isolation_effect" value="8.0"><property id="average distance" value="2.5"/><property id="shortest distance" value="2.5"/></link><link source="loss" target="comply_effect" value="4.0"><property id="average distance" value="2.5"/><property id="shortest distance" value="2.5"/></link><link source="loss" target="judging" value="10.0"><property id="average distance" value="12.0"/><property id="shortest distance" value="12.0"/></link><link source="loss" target="internalization" value="6.0"><property id="average distance" value="3.0"/><property id="shortest distance" value="3.0"/></link><link source="loss" target="&#64258;" value="2.0"><property id="average distance" value="1.0"/><property id="shortest distance" value="1.0"/></link><link source="loss" target="syllogistic_rules" value="2.0"><property id="average distance" value="2.0"/><property id="shortest distance" value="2.0"/></link><link source="loss" target="gain" value="14.0"><property id="average distance" value="8.285714"/><property id="shortest distance" value="8.285714"/></link><link source="loss" target="personality" value="60.0"><property id="average distance" value="10.4"/><property id="shortest distance" value="10.4"/></link><link source="generalizing" target="function" value="2.0"><property id="average distance" value="1.0"/><property id="shortest distance" value="1.0"/></link><link source="generalizing" target="personality" value="4.0"><property id="average distance" value="1.5"/><property id="shortest distance" value="1.5"/></link><link source="physical_quality" target="intrinsic_rewards" value="2.0"><property id="average distance" value="2.0"/><property id="shortest distance" value="2.0"/></link><link source="physical_quality" target="&#64257;" value="2.0"><property id="average distance" value="3.0"/><property id="shortest distance" value="3.0"/></link><link source="physical_quality" target="possibility_effect" value="2.0"><property id="average distance" value="1.0"/><property id="shortest distance" value="1.0"/></link><link source="&#64258;" target="focus" value="2.0"><property id="average distance" value="1.0"/><property id="shortest distance" value="1.0"/></link><link source="&#64258;" target="participant_modeling" value="2.0"><property id="average distance" value="2.0"/><property id="shortest distance" value="2.0"/></link><link source="&#64258;" target="&#64257;" value="4.0"><property id="average distance" value="1.25"/><property id="shortest distance" value="1.5"/></link><link source="&#64258;" target="loss" value="2.0"><property id="average distance" value="1.0"/><property id="shortest distance" value="1.0"/></link><link source="&#64258;" target="possibility_effect" value="2.0"><property id="average distance" value="1.0"/><property id="shortest distance" value="1.0"/></link><link source="internalization" target="loss" value="6.0"><property id="average distance" value="3.0"/><property id="shortest distance" value="3.0"/></link><link source="internalization" target="possibility_effect" value="2.0"><property id="average distance" value="1.0"/><property id="shortest distance" value="1.0"/></link><link source="syllogistic_rules" target="intentionality" value="2.0"><property id="average distance" value="1.0"/><property id="shortest distance" value="1.0"/></link><link source="syllogistic_rules" target="mental_calculation" value="4.0"><property id="average distance" value="2.5"/><property id="shortest distance" value="2.5"/></link><link source="syllogistic_rules" target="personality" value="2.0"><property id="average distance" value="1.0"/><property id="shortest distance" value="1.0"/></link><link source="syllogistic_rules" target="loss" value="2.0"><property id="average distance" value="2.0"/><property id="shortest distance" value="2.0"/></link><link source="gain" target="protection_effect" value="2.0"><property id="average distance" value="1.0"/><property id="shortest distance" value="1.0"/></link><link source="gain" target="comply_effect" value="2.0"><property id="average distance" value="1.0"/><property id="shortest distance" value="1.0"/></link><link source="gain" target="appraisal" value="4.0"><property id="average distance" value="2.0"/><property id="shortest distance" value="2.0"/></link><link source="gain" target="mental_calculation" value="2.0"><property id="average distance" value="1.0"/><property id="shortest distance" value="1.0"/></link><link source="gain" target="judging" value="4.0"><property id="average distance" value="2.0"/><property id="shortest distance" value="2.0"/></link><link source="gain" target="perceived_vulnerability" value="30.0"><property id="average distance" value="10.0"/><property id="shortest distance" value="10.0"/></link><link source="gain" target="social_circumstance" value="2.0"><property id="average distance" value="4.0"/><property id="shortest distance" value="4.0"/></link><link source="gain" target="loss" value="14.0"><property id="average distance" value="8.285714"/><property id="shortest distance" value="8.285714"/></link><link source="gain" target="evaluating" value="4.0"><property id="average distance" value="23.0"/><property id="shortest distance" value="23.0"/></link><link source="gain" target="certainty_effect" value="10.0"><property id="average distance" value="12.8"/><property id="shortest distance" value="12.8"/></link><link source="gain" target="function" value="2.0"><property id="average distance" value="1.0"/><property id="shortest distance" value="1.0"/></link><link source="gain" target="personality" value="12.0"><property id="average distance" value="4.3333335"/><property id="shortest distance" value="4.3333335"/></link><link source="gain" target="behavior" value="6.0"><property id="average distance" value="1.3333334"/><property id="shortest distance" value="1.3333334"/></link><link source="personality" target="protection_effect" value="2.0"><property id="average distance" value="2.0"/><property id="shortest distance" value="2.0"/></link><link source="personality" target="division" value="2.0"><property id="average distance" value="1.0"/><property id="shortest distance" value="1.0"/></link><link source="personality" target="appraisal" value="18.0"><property id="average distance" value="3.4444444"/><property id="shortest distance" value="3.4444444"/></link><link source="personality" target="learning" value="2.0"><property id="average distance" value="3.0"/><property id="shortest distance" value="3.0"/></link><link source="personality" target="mental_calculation" value="10.0"><property id="average distance" value="1.2"/><property id="shortest distance" value="1.2"/></link><link source="personality" target="&#64257;" value="36.0"><property id="average distance" value="1.6666666"/><property id="shortest distance" value="1.6666666"/></link><link source="personality" target="perceived_vulnerability" value="174.0"><property id="average distance" value="9.873563"/><property id="shortest distance" value="9.873563"/></link><link source="personality" target="social_circumstance" value="12.0"><property id="average distance" value="6.0"/><property id="shortest distance" value="6.0"/></link><link source="personality" target="simplifying" value="6.0"><property id="average distance" value="1.0"/><property id="shortest distance" value="1.0"/></link><link source="personality" target="evaluating" value="32.0"><property id="average distance" value="16.6875"/><property id="shortest distance" value="16.6875"/></link><link source="personality" target="certainty_effect" value="68.0"><property id="average distance" value="10.411765"/><property id="shortest distance" value="10.411765"/></link><link source="personality" target="function" value="8.0"><property id="average distance" value="1.25"/><property id="shortest distance" value="1.25"/></link><link source="personality" target="process" value="10.0"><property id="average distance" value="2.2"/><property id="shortest distance" value="2.2"/></link><link source="personality" target="intrinsic_rewards" value="2.0"><property id="average distance" value="1.0"/><property id="shortest distance" value="1.0"/></link><link source="personality" target="participant_modeling" value="16.0"><property id="average distance" value="1.625"/><property id="shortest distance" value="1.625"/></link><link source="personality" target="goal" value="2.0"><property id="average distance" value="2.0"/><property id="shortest distance" value="2.0"/></link><link source="personality" target="behavior" value="6.0"><property id="average distance" value="1.6666666"/><property id="shortest distance" value="1.6666666"/></link><link source="personality" target="possibility_effect" value="6.0"><property id="average distance" value="1.3333334"/><property id="shortest distance" value="1.3333334"/></link><link source="personality" target="combining" value="4.0"><property id="average distance" value="1.5"/><property id="shortest distance" value="1.5"/></link><link source="personality" target="isolation_effect" value="12.0"><property id="average distance" value="1.3333334"/><property id="shortest distance" value="1.3333334"/></link><link source="personality" target="comply_effect" value="12.0"><property id="average distance" value="1.5"/><property id="shortest distance" value="1.5"/></link><link source="personality" target="segregating" value="4.0"><property id="average distance" value="2.5"/><property id="shortest distance" value="2.5"/></link><link source="personality" target="judging" value="16.0"><property id="average distance" value="4.625"/><property id="shortest distance" value="4.625"/></link><link source="personality" target="loss" value="60.0"><property id="average distance" value="10.4"/><property id="shortest distance" value="10.4"/></link><link source="personality" target="generalizing" value="4.0"><property id="average distance" value="1.5"/><property id="shortest distance" value="1.5"/></link><link source="personality" target="syllogistic_rules" value="2.0"><property id="average distance" value="1.0"/><property id="shortest distance" value="1.0"/></link><link source="personality" target="gain" value="12.0"><property id="average distance" value="4.3333335"/><property id="shortest distance" value="4.3333335"/></link></network><network sourceType="Belief" source="Belief" targetType="Unknown" target="Unknown" id="Belief x Unknown" isDirected="true" allowSelfLoops="true" isBinary="false"><propertyIdentities><propertyIdentity id="average distance" type="number" singleValued="false"/><propertyIdentity id="shortest distance" type="number" singleValued="false"/></propertyIdentities><link source="belief" target="evaluating" value="2.0"><property id="average distance" value="1.0"/><property id="shortest distance" value="1.0"/></link><link source="belief" target="isolation_effect" value="2.0"><property id="average distance" value="2.0"/><property id="shortest distance" value="2.0"/></link><link source="belief" target="learning" value="2.0"><property id="average distance" value="2.0"/><property id="shortest distance" value="2.0"/></link><link source="belief" target="&#64257;" value="4.0"><property id="average distance" value="1.5"/><property id="shortest distance" value="1.5"/></link><link source="belief" target="personality" value="2.0"><property id="average distance" value="3.0"/><property id="shortest distance" value="3.0"/></link><link source="belief" target="behavior" value="4.0"><property id="average distance" value="2.0"/><property id="shortest distance" value="2.0"/></link><link source="belief" target="perceived_vulnerability" value="2.0"><property id="average distance" value="1.0"/><property id="shortest distance" value="1.0"/></link><link source="belief" target="coding" value="2.0"><property id="average distance" value="1.0"/><property id="shortest distance" value="1.0"/></link><link source="belief" target="loss" value="4.0"><property id="average distance" value="4.5"/><property id="shortest distance" value="4.5"/></link></network><network sourceType="Resource" source="Resource" targetType="Unknown" target="Unknown" id="Resource x Unknown" isDirected="true" allowSelfLoops="true" isBinary="false"><propertyIdentities><propertyIdentity id="average distance" type="number" singleValued="false"/><propertyIdentity id="shortest distance" type="number" singleValued="false"/></propertyIdentities><link source="resource" target="&#64257;&#64257;&#64257;" value="2.0"><property id="shortest distance" value="1.0"/><property id="average distance" value="1.0"/></link></network></networks></MetaNetwork></DynamicNetwork>

